[
  {
    "time_hours": 0,
    "approval_perbill": 1000000000,
    "support_perbill": 500000038,
    "approval": 100,
    "support": 50.0000038
  },
  {
    "time_hours": 1,
    "approval_perbill": 997916667,
    "support_perbill": 422810379,
    "approval": 99.7916667,
    "support": 42.2810379
  },
  {
    "time_hours": 2,
    "approval_perbill": 995833334,
    "support_perbill": 366120266,
    "approval": 99.5833334,
    "support": 36.6120266
  },
  {
    "time_hours": 3,
    "approval_perbill": 993750001,
    "support_perbill": 322720742,
    "approval": 99.3750001,
    "support": 32.2720742
  },
  {
    "time_hours": 4,
    "approval_perbill": 991666668,
    "support_perbill": 288428371,
    "approval": 99.1666668,
    "support": 28.8428371
  },
  {
    "time_hours": 5,
    "approval_perbill": 989583334,
    "support_perbill": 260648719,
    "approval": 98.9583334,
    "support": 26.0648719
  },
  {
    "time_hours": 6,
    "approval_perbill": 987500001,
    "support_perbill": 237687395,
    "approval": 98.7500001,
    "support": 23.7687395
  },
  {
    "time_hours": 7,
    "approval_perbill": 985416668,
    "support_perbill": 218390834,
    "approval": 98.5416668,
    "support": 21.8390834
  },
  {
    "time_hours": 8,
    "approval_perbill": 983333335,
    "support_perbill": 201946501,
    "approval": 98.3333335,
    "support": 20.1946501
  },
  {
    "time_hours": 9,
    "approval_perbill": 981250001,
    "support_perbill": 187765525,
    "approval": 98.1250001,
    "support": 18.7765525
  },
  {
    "time_hours": 10,
    "approval_perbill": 979166668,
    "support_perbill": 175410725,
    "approval": 97.9166668,
    "support": 17.5410725
  },
  {
    "time_hours": 11,
    "approval_perbill": 977083335,
    "support_perbill": 164550680,
    "approval": 97.7083335,
    "support": 16.455068
  },
  {
    "time_hours": 12,
    "approval_perbill": 975000002,
    "support_perbill": 154929598,
    "approval": 97.5000002,
    "support": 15.4929598
  },
  {
    "time_hours": 13,
    "approval_perbill": 972916667,
    "support_perbill": 146346895,
    "approval": 97.2916667,
    "support": 14.6346895
  },
  {
    "time_hours": 14,
    "approval_perbill": 970833334,
    "support_perbill": 138643083,
    "approval": 97.0833334,
    "support": 13.8643083
  },
  {
    "time_hours": 15,
    "approval_perbill": 968750001,
    "support_perbill": 131689733,
    "approval": 96.8750001,
    "support": 13.1689733
  },
  {
    "time_hours": 16,
    "approval_perbill": 966666668,
    "support_perbill": 125382279,
    "approval": 96.6666668,
    "support": 12.5382279
  },
  {
    "time_hours": 17,
    "approval_perbill": 964583334,
    "support_perbill": 119634716,
    "approval": 96.4583334,
    "support": 11.9634716
  },
  {
    "time_hours": 18,
    "approval_perbill": 962500001,
    "support_perbill": 114375668,
    "approval": 96.2500001,
    "support": 11.4375668
  },
  {
    "time_hours": 19,
    "approval_perbill": 960416668,
    "support_perbill": 109545391,
    "approval": 96.0416668,
    "support": 10.9545391
  },
  {
    "time_hours": 20,
    "approval_perbill": 958333335,
    "support_perbill": 105093501,
    "approval": 95.8333335,
    "support": 10.5093501
  },
  {
    "time_hours": 21,
    "approval_perbill": 956250000,
    "support_perbill": 100977209,
    "approval": 95.625,
    "support": 10.0977209
  },
  {
    "time_hours": 22,
    "approval_perbill": 954166667,
    "support_perbill": 97159951,
    "approval": 95.4166667,
    "support": 9.7159951
  },
  {
    "time_hours": 23,
    "approval_perbill": 952083334,
    "support_perbill": 93610280,
    "approval": 95.2083334,
    "support": 9.361028
  },
  {
    "time_hours": 24,
    "approval_perbill": 950000001,
    "support_perbill": 90301014,
    "approval": 95.0000001,
    "support": 9.0301014
  },
  {
    "time_hours": 25,
    "approval_perbill": 947916668,
    "support_perbill": 87208529,
    "approval": 94.7916668,
    "support": 8.7208529
  },
  {
    "time_hours": 26,
    "approval_perbill": 945833334,
    "support_perbill": 84312199,
    "approval": 94.5833334,
    "support": 8.4312199
  },
  {
    "time_hours": 27,
    "approval_perbill": 943750001,
    "support_perbill": 81593937,
    "approval": 94.3750001,
    "support": 8.1593937
  },
  {
    "time_hours": 28,
    "approval_perbill": 941666668,
    "support_perbill": 79037810,
    "approval": 94.1666668,
    "support": 7.903781
  },
  {
    "time_hours": 29,
    "approval_perbill": 939583335,
    "support_perbill": 76629732,
    "approval": 93.9583335,
    "support": 7.6629732
  },
  {
    "time_hours": 30,
    "approval_perbill": 937500001,
    "support_perbill": 74357200,
    "approval": 93.7500001,
    "support": 7.43572
  },
  {
    "time_hours": 31,
    "approval_perbill": 935416668,
    "support_perbill": 72209088,
    "approval": 93.5416668,
    "support": 7.2209088
  },
  {
    "time_hours": 32,
    "approval_perbill": 933333335,
    "support_perbill": 70175447,
    "approval": 93.3333335,
    "support": 7.0175447
  },
  {
    "time_hours": 33,
    "approval_perbill": 931250002,
    "support_perbill": 68247365,
    "approval": 93.1250002,
    "support": 6.8247365
  },
  {
    "time_hours": 34,
    "approval_perbill": 929166667,
    "support_perbill": 66416830,
    "approval": 92.9166667,
    "support": 6.641683
  },
  {
    "time_hours": 35,
    "approval_perbill": 927083334,
    "support_perbill": 64676624,
    "approval": 92.7083334,
    "support": 6.4676624
  },
  {
    "time_hours": 36,
    "approval_perbill": 925000001,
    "support_perbill": 63020221,
    "approval": 92.5000001,
    "support": 6.3020221
  },
  {
    "time_hours": 37,
    "approval_perbill": 922916668,
    "support_perbill": 61441710,
    "approval": 92.2916668,
    "support": 6.144171
  },
  {
    "time_hours": 38,
    "approval_perbill": 920833334,
    "support_perbill": 59935722,
    "approval": 92.0833334,
    "support": 5.9935722
  },
  {
    "time_hours": 39,
    "approval_perbill": 918750001,
    "support_perbill": 58497372,
    "approval": 91.8750001,
    "support": 5.8497372
  },
  {
    "time_hours": 40,
    "approval_perbill": 916666668,
    "support_perbill": 57122204,
    "approval": 91.6666668,
    "support": 5.7122204
  },
  {
    "time_hours": 41,
    "approval_perbill": 914583335,
    "support_perbill": 55806144,
    "approval": 91.4583335,
    "support": 5.5806144
  },
  {
    "time_hours": 42,
    "approval_perbill": 912500000,
    "support_perbill": 54545460,
    "approval": 91.25,
    "support": 5.454546
  },
  {
    "time_hours": 43,
    "approval_perbill": 910416667,
    "support_perbill": 53336731,
    "approval": 91.0416667,
    "support": 5.3336731
  },
  {
    "time_hours": 44,
    "approval_perbill": 908333334,
    "support_perbill": 52176808,
    "approval": 90.8333334,
    "support": 5.2176808
  },
  {
    "time_hours": 45,
    "approval_perbill": 906250001,
    "support_perbill": 51062796,
    "approval": 90.6250001,
    "support": 5.1062796
  },
  {
    "time_hours": 46,
    "approval_perbill": 904166668,
    "support_perbill": 49992020,
    "approval": 90.4166668,
    "support": 4.999202
  },
  {
    "time_hours": 47,
    "approval_perbill": 902083334,
    "support_perbill": 48962010,
    "approval": 90.2083334,
    "support": 4.896201
  },
  {
    "time_hours": 48,
    "approval_perbill": 900000001,
    "support_perbill": 47970485,
    "approval": 90.0000001,
    "support": 4.7970485
  },
  {
    "time_hours": 49,
    "approval_perbill": 897916668,
    "support_perbill": 47015325,
    "approval": 89.7916668,
    "support": 4.7015325
  },
  {
    "time_hours": 50,
    "approval_perbill": 895833335,
    "support_perbill": 46094566,
    "approval": 89.5833335,
    "support": 4.6094566
  },
  {
    "time_hours": 51,
    "approval_perbill": 893750001,
    "support_perbill": 45206381,
    "approval": 89.3750001,
    "support": 4.5206381
  },
  {
    "time_hours": 52,
    "approval_perbill": 891666668,
    "support_perbill": 44349075,
    "approval": 89.1666668,
    "support": 4.4349075
  },
  {
    "time_hours": 53,
    "approval_perbill": 889583335,
    "support_perbill": 43521062,
    "approval": 88.9583335,
    "support": 4.3521062
  },
  {
    "time_hours": 54,
    "approval_perbill": 887500002,
    "support_perbill": 42720867,
    "approval": 88.7500002,
    "support": 4.2720867
  },
  {
    "time_hours": 55,
    "approval_perbill": 885416667,
    "support_perbill": 41947111,
    "approval": 88.5416667,
    "support": 4.1947111
  },
  {
    "time_hours": 56,
    "approval_perbill": 883333334,
    "support_perbill": 41198506,
    "approval": 88.3333334,
    "support": 4.1198506
  },
  {
    "time_hours": 57,
    "approval_perbill": 881250001,
    "support_perbill": 40473844,
    "approval": 88.1250001,
    "support": 4.0473844
  },
  {
    "time_hours": 58,
    "approval_perbill": 879166668,
    "support_perbill": 39771995,
    "approval": 87.9166668,
    "support": 3.9771995
  },
  {
    "time_hours": 59,
    "approval_perbill": 877083334,
    "support_perbill": 39091898,
    "approval": 87.7083334,
    "support": 3.9091898
  },
  {
    "time_hours": 60,
    "approval_perbill": 875000001,
    "support_perbill": 38432558,
    "approval": 87.5000001,
    "support": 3.8432558
  },
  {
    "time_hours": 61,
    "approval_perbill": 872916668,
    "support_perbill": 37793039,
    "approval": 87.2916668,
    "support": 3.7793039
  },
  {
    "time_hours": 62,
    "approval_perbill": 870833335,
    "support_perbill": 37172460,
    "approval": 87.0833335,
    "support": 3.717246
  },
  {
    "time_hours": 63,
    "approval_perbill": 868750000,
    "support_perbill": 36569991,
    "approval": 86.875,
    "support": 3.6569991
  },
  {
    "time_hours": 64,
    "approval_perbill": 866666667,
    "support_perbill": 35984852,
    "approval": 86.6666667,
    "support": 3.5984852
  },
  {
    "time_hours": 65,
    "approval_perbill": 864583334,
    "support_perbill": 35416306,
    "approval": 86.4583334,
    "support": 3.5416306
  },
  {
    "time_hours": 66,
    "approval_perbill": 862500001,
    "support_perbill": 34863656,
    "approval": 86.2500001,
    "support": 3.4863656
  },
  {
    "time_hours": 67,
    "approval_perbill": 860416668,
    "support_perbill": 34326245,
    "approval": 86.0416668,
    "support": 3.4326245
  },
  {
    "time_hours": 68,
    "approval_perbill": 858333334,
    "support_perbill": 33803451,
    "approval": 85.8333334,
    "support": 3.3803451
  },
  {
    "time_hours": 69,
    "approval_perbill": 856250001,
    "support_perbill": 33294686,
    "approval": 85.6250001,
    "support": 3.3294686
  },
  {
    "time_hours": 70,
    "approval_perbill": 854166668,
    "support_perbill": 32799393,
    "approval": 85.4166668,
    "support": 3.2799393
  },
  {
    "time_hours": 71,
    "approval_perbill": 852083335,
    "support_perbill": 32317044,
    "approval": 85.2083335,
    "support": 3.2317044
  },
  {
    "time_hours": 72,
    "approval_perbill": 850000001,
    "support_perbill": 31847137,
    "approval": 85.0000001,
    "support": 3.1847137
  },
  {
    "time_hours": 73,
    "approval_perbill": 847916668,
    "support_perbill": 31389198,
    "approval": 84.7916668,
    "support": 3.1389198
  },
  {
    "time_hours": 74,
    "approval_perbill": 845833335,
    "support_perbill": 30942774,
    "approval": 84.5833335,
    "support": 3.0942774
  },
  {
    "time_hours": 75,
    "approval_perbill": 843750002,
    "support_perbill": 30507438,
    "approval": 84.3750002,
    "support": 3.0507438
  },
  {
    "time_hours": 76,
    "approval_perbill": 841666667,
    "support_perbill": 30082781,
    "approval": 84.1666667,
    "support": 3.0082781
  },
  {
    "time_hours": 77,
    "approval_perbill": 839583334,
    "support_perbill": 29668415,
    "approval": 83.9583334,
    "support": 2.9668415
  },
  {
    "time_hours": 78,
    "approval_perbill": 837500001,
    "support_perbill": 29263970,
    "approval": 83.7500001,
    "support": 2.926397
  },
  {
    "time_hours": 79,
    "approval_perbill": 835416668,
    "support_perbill": 28869094,
    "approval": 83.5416668,
    "support": 2.8869094
  },
  {
    "time_hours": 80,
    "approval_perbill": 833333334,
    "support_perbill": 28483451,
    "approval": 83.3333334,
    "support": 2.8483451
  },
  {
    "time_hours": 81,
    "approval_perbill": 831250001,
    "support_perbill": 28106723,
    "approval": 83.1250001,
    "support": 2.8106723
  },
  {
    "time_hours": 82,
    "approval_perbill": 829166668,
    "support_perbill": 27738602,
    "approval": 82.9166668,
    "support": 2.7738602
  },
  {
    "time_hours": 83,
    "approval_perbill": 827083335,
    "support_perbill": 27378797,
    "approval": 82.7083335,
    "support": 2.7378797
  },
  {
    "time_hours": 84,
    "approval_perbill": 825000000,
    "support_perbill": 27027029,
    "approval": 82.5,
    "support": 2.7027029
  },
  {
    "time_hours": 85,
    "approval_perbill": 822916667,
    "support_perbill": 26683033,
    "approval": 82.2916667,
    "support": 2.6683033
  },
  {
    "time_hours": 86,
    "approval_perbill": 820833334,
    "support_perbill": 26346554,
    "approval": 82.0833334,
    "support": 2.6346554
  },
  {
    "time_hours": 87,
    "approval_perbill": 818750001,
    "support_perbill": 26017347,
    "approval": 81.8750001,
    "support": 2.6017347
  },
  {
    "time_hours": 88,
    "approval_perbill": 816666668,
    "support_perbill": 25695180,
    "approval": 81.6666668,
    "support": 2.569518
  },
  {
    "time_hours": 89,
    "approval_perbill": 814583334,
    "support_perbill": 25379829,
    "approval": 81.4583334,
    "support": 2.5379829
  },
  {
    "time_hours": 90,
    "approval_perbill": 812500001,
    "support_perbill": 25071080,
    "approval": 81.2500001,
    "support": 2.507108
  },
  {
    "time_hours": 91,
    "approval_perbill": 810416668,
    "support_perbill": 24768728,
    "approval": 81.0416668,
    "support": 2.4768728
  },
  {
    "time_hours": 92,
    "approval_perbill": 808333335,
    "support_perbill": 24472576,
    "approval": 80.8333335,
    "support": 2.4472576
  },
  {
    "time_hours": 93,
    "approval_perbill": 806250001,
    "support_perbill": 24182435,
    "approval": 80.6250001,
    "support": 2.4182435
  },
  {
    "time_hours": 94,
    "approval_perbill": 804166668,
    "support_perbill": 23898125,
    "approval": 80.4166668,
    "support": 2.3898125
  },
  {
    "time_hours": 95,
    "approval_perbill": 802083335,
    "support_perbill": 23619471,
    "approval": 80.2083335,
    "support": 2.3619471
  },
  {
    "time_hours": 96,
    "approval_perbill": 800000002,
    "support_perbill": 23346306,
    "approval": 80.0000002,
    "support": 2.3346306
  },
  {
    "time_hours": 97,
    "approval_perbill": 797916667,
    "support_perbill": 23078469,
    "approval": 79.7916667,
    "support": 2.3078469
  },
  {
    "time_hours": 98,
    "approval_perbill": 795833334,
    "support_perbill": 22815806,
    "approval": 79.5833334,
    "support": 2.2815806
  },
  {
    "time_hours": 99,
    "approval_perbill": 793750001,
    "support_perbill": 22558169,
    "approval": 79.3750001,
    "support": 2.2558169
  },
  {
    "time_hours": 100,
    "approval_perbill": 791666668,
    "support_perbill": 22305415,
    "approval": 79.1666668,
    "support": 2.2305415
  },
  {
    "time_hours": 101,
    "approval_perbill": 789583334,
    "support_perbill": 22057405,
    "approval": 78.9583334,
    "support": 2.2057405
  },
  {
    "time_hours": 102,
    "approval_perbill": 787500001,
    "support_perbill": 21814009,
    "approval": 78.7500001,
    "support": 2.1814009
  },
  {
    "time_hours": 103,
    "approval_perbill": 785416668,
    "support_perbill": 21575098,
    "approval": 78.5416668,
    "support": 2.1575098
  },
  {
    "time_hours": 104,
    "approval_perbill": 783333335,
    "support_perbill": 21340549,
    "approval": 78.3333335,
    "support": 2.1340549
  },
  {
    "time_hours": 105,
    "approval_perbill": 781250000,
    "support_perbill": 21110244,
    "approval": 78.125,
    "support": 2.1110244
  },
  {
    "time_hours": 106,
    "approval_perbill": 779166667,
    "support_perbill": 20884069,
    "approval": 77.9166667,
    "support": 2.0884069
  },
  {
    "time_hours": 107,
    "approval_perbill": 777083334,
    "support_perbill": 20661914,
    "approval": 77.7083334,
    "support": 2.0661914
  },
  {
    "time_hours": 108,
    "approval_perbill": 775000001,
    "support_perbill": 20443673,
    "approval": 77.5000001,
    "support": 2.0443673
  },
  {
    "time_hours": 109,
    "approval_perbill": 772916668,
    "support_perbill": 20229243,
    "approval": 77.2916668,
    "support": 2.0229243
  },
  {
    "time_hours": 110,
    "approval_perbill": 770833334,
    "support_perbill": 20018524,
    "approval": 77.0833334,
    "support": 2.0018524
  },
  {
    "time_hours": 111,
    "approval_perbill": 768750001,
    "support_perbill": 19811422,
    "approval": 76.8750001,
    "support": 1.9811422
  },
  {
    "time_hours": 112,
    "approval_perbill": 766666668,
    "support_perbill": 19607845,
    "approval": 76.6666668,
    "support": 1.9607845
  },
  {
    "time_hours": 113,
    "approval_perbill": 764583335,
    "support_perbill": 19407702,
    "approval": 76.4583335,
    "support": 1.9407702
  },
  {
    "time_hours": 114,
    "approval_perbill": 762500001,
    "support_perbill": 19210908,
    "approval": 76.2500001,
    "support": 1.9210908
  },
  {
    "time_hours": 115,
    "approval_perbill": 760416668,
    "support_perbill": 19017380,
    "approval": 76.0416668,
    "support": 1.901738
  },
  {
    "time_hours": 116,
    "approval_perbill": 758333335,
    "support_perbill": 18827037,
    "approval": 75.8333335,
    "support": 1.8827037
  },
  {
    "time_hours": 117,
    "approval_perbill": 756250002,
    "support_perbill": 18639800,
    "approval": 75.6250002,
    "support": 1.86398
  },
  {
    "time_hours": 118,
    "approval_perbill": 754166667,
    "support_perbill": 18455595,
    "approval": 75.4166667,
    "support": 1.8455595
  },
  {
    "time_hours": 119,
    "approval_perbill": 752083334,
    "support_perbill": 18274348,
    "approval": 75.2083334,
    "support": 1.8274348
  },
  {
    "time_hours": 120,
    "approval_perbill": 750000001,
    "support_perbill": 18095989,
    "approval": 75.0000001,
    "support": 1.8095989
  },
  {
    "time_hours": 121,
    "approval_perbill": 747916668,
    "support_perbill": 17920449,
    "approval": 74.7916668,
    "support": 1.7920449
  },
  {
    "time_hours": 122,
    "approval_perbill": 745833334,
    "support_perbill": 17747662,
    "approval": 74.5833334,
    "support": 1.7747662
  },
  {
    "time_hours": 123,
    "approval_perbill": 743750001,
    "support_perbill": 17577564,
    "approval": 74.3750001,
    "support": 1.7577564
  },
  {
    "time_hours": 124,
    "approval_perbill": 741666668,
    "support_perbill": 17410092,
    "approval": 74.1666668,
    "support": 1.7410092
  },
  {
    "time_hours": 125,
    "approval_perbill": 739583335,
    "support_perbill": 17245186,
    "approval": 73.9583335,
    "support": 1.7245186
  },
  {
    "time_hours": 126,
    "approval_perbill": 737500000,
    "support_perbill": 17082787,
    "approval": 73.75,
    "support": 1.7082787
  },
  {
    "time_hours": 127,
    "approval_perbill": 735416667,
    "support_perbill": 16922839,
    "approval": 73.5416667,
    "support": 1.6922839
  },
  {
    "time_hours": 128,
    "approval_perbill": 733333334,
    "support_perbill": 16765287,
    "approval": 73.3333334,
    "support": 1.6765287
  },
  {
    "time_hours": 129,
    "approval_perbill": 731250001,
    "support_perbill": 16610077,
    "approval": 73.1250001,
    "support": 1.6610077
  },
  {
    "time_hours": 130,
    "approval_perbill": 729166668,
    "support_perbill": 16457158,
    "approval": 72.9166668,
    "support": 1.6457158
  },
  {
    "time_hours": 131,
    "approval_perbill": 727083334,
    "support_perbill": 16306479,
    "approval": 72.7083334,
    "support": 1.6306479
  },
  {
    "time_hours": 132,
    "approval_perbill": 725000001,
    "support_perbill": 16157990,
    "approval": 72.5000001,
    "support": 1.615799
  },
  {
    "time_hours": 133,
    "approval_perbill": 722916668,
    "support_perbill": 16011646,
    "approval": 72.2916668,
    "support": 1.6011646
  },
  {
    "time_hours": 134,
    "approval_perbill": 720833335,
    "support_perbill": 15867399,
    "approval": 72.0833335,
    "support": 1.5867399
  },
  {
    "time_hours": 135,
    "approval_perbill": 718750001,
    "support_perbill": 15725205,
    "approval": 71.8750001,
    "support": 1.5725205
  },
  {
    "time_hours": 136,
    "approval_perbill": 716666668,
    "support_perbill": 15585021,
    "approval": 71.6666668,
    "support": 1.5585021
  },
  {
    "time_hours": 137,
    "approval_perbill": 714583335,
    "support_perbill": 15446804,
    "approval": 71.4583335,
    "support": 1.5446804
  },
  {
    "time_hours": 138,
    "approval_perbill": 712500002,
    "support_perbill": 15310512,
    "approval": 71.2500002,
    "support": 1.5310512
  },
  {
    "time_hours": 139,
    "approval_perbill": 710416667,
    "support_perbill": 15176107,
    "approval": 71.0416667,
    "support": 1.5176107
  },
  {
    "time_hours": 140,
    "approval_perbill": 708333334,
    "support_perbill": 15043548,
    "approval": 70.8333334,
    "support": 1.5043548
  },
  {
    "time_hours": 141,
    "approval_perbill": 706250001,
    "support_perbill": 14912799,
    "approval": 70.6250001,
    "support": 1.4912799
  },
  {
    "time_hours": 142,
    "approval_perbill": 704166668,
    "support_perbill": 14783823,
    "approval": 70.4166668,
    "support": 1.4783823
  },
  {
    "time_hours": 143,
    "approval_perbill": 702083334,
    "support_perbill": 14656583,
    "approval": 70.2083334,
    "support": 1.4656583
  },
  {
    "time_hours": 144,
    "approval_perbill": 700000001,
    "support_perbill": 14531045,
    "approval": 70.0000001,
    "support": 1.4531045
  },
  {
    "time_hours": 145,
    "approval_perbill": 697916668,
    "support_perbill": 14407175,
    "approval": 69.7916668,
    "support": 1.4407175
  },
  {
    "time_hours": 146,
    "approval_perbill": 695833335,
    "support_perbill": 14284939,
    "approval": 69.5833335,
    "support": 1.4284939
  },
  {
    "time_hours": 147,
    "approval_perbill": 693750000,
    "support_perbill": 14164307,
    "approval": 69.375,
    "support": 1.4164307
  },
  {
    "time_hours": 148,
    "approval_perbill": 691666667,
    "support_perbill": 14045246,
    "approval": 69.1666667,
    "support": 1.4045246
  },
  {
    "time_hours": 149,
    "approval_perbill": 689583334,
    "support_perbill": 13927726,
    "approval": 68.9583334,
    "support": 1.3927726
  },
  {
    "time_hours": 150,
    "approval_perbill": 687500001,
    "support_perbill": 13811717,
    "approval": 68.7500001,
    "support": 1.3811717
  },
  {
    "time_hours": 151,
    "approval_perbill": 685416668,
    "support_perbill": 13697191,
    "approval": 68.5416668,
    "support": 1.3697191
  },
  {
    "time_hours": 152,
    "approval_perbill": 683333334,
    "support_perbill": 13584118,
    "approval": 68.3333334,
    "support": 1.3584118
  },
  {
    "time_hours": 153,
    "approval_perbill": 681250001,
    "support_perbill": 13472472,
    "approval": 68.1250001,
    "support": 1.3472472
  },
  {
    "time_hours": 154,
    "approval_perbill": 679166668,
    "support_perbill": 13362226,
    "approval": 67.9166668,
    "support": 1.3362226
  },
  {
    "time_hours": 155,
    "approval_perbill": 677083335,
    "support_perbill": 13253353,
    "approval": 67.7083335,
    "support": 1.3253353
  },
  {
    "time_hours": 156,
    "approval_perbill": 675000001,
    "support_perbill": 13145828,
    "approval": 67.5000001,
    "support": 1.3145828
  },
  {
    "time_hours": 157,
    "approval_perbill": 672916668,
    "support_perbill": 13039626,
    "approval": 67.2916668,
    "support": 1.3039626
  },
  {
    "time_hours": 158,
    "approval_perbill": 670833335,
    "support_perbill": 12934723,
    "approval": 67.0833335,
    "support": 1.2934723
  },
  {
    "time_hours": 159,
    "approval_perbill": 668750002,
    "support_perbill": 12831096,
    "approval": 66.8750002,
    "support": 1.2831096
  },
  {
    "time_hours": 160,
    "approval_perbill": 666666667,
    "support_perbill": 12728720,
    "approval": 66.6666667,
    "support": 1.272872
  },
  {
    "time_hours": 161,
    "approval_perbill": 664583334,
    "support_perbill": 12627574,
    "approval": 66.4583334,
    "support": 1.2627574
  },
  {
    "time_hours": 162,
    "approval_perbill": 662500001,
    "support_perbill": 12527635,
    "approval": 66.2500001,
    "support": 1.2527635
  },
  {
    "time_hours": 163,
    "approval_perbill": 660416668,
    "support_perbill": 12428883,
    "approval": 66.0416668,
    "support": 1.2428883
  },
  {
    "time_hours": 164,
    "approval_perbill": 658333334,
    "support_perbill": 12331295,
    "approval": 65.8333334,
    "support": 1.2331295
  },
  {
    "time_hours": 165,
    "approval_perbill": 656250001,
    "support_perbill": 12234852,
    "approval": 65.6250001,
    "support": 1.2234852
  },
  {
    "time_hours": 166,
    "approval_perbill": 654166668,
    "support_perbill": 12139533,
    "approval": 65.4166668,
    "support": 1.2139533
  },
  {
    "time_hours": 167,
    "approval_perbill": 652083335,
    "support_perbill": 12045320,
    "approval": 65.2083335,
    "support": 1.204532
  },
  {
    "time_hours": 168,
    "approval_perbill": 650000000,
    "support_perbill": 11952192,
    "approval": 65,
    "support": 1.1952192
  },
  {
    "time_hours": 169,
    "approval_perbill": 647916667,
    "support_perbill": 11860131,
    "approval": 64.7916667,
    "support": 1.1860131
  },
  {
    "time_hours": 170,
    "approval_perbill": 645833334,
    "support_perbill": 11769120,
    "approval": 64.5833334,
    "support": 1.176912
  },
  {
    "time_hours": 171,
    "approval_perbill": 643750001,
    "support_perbill": 11679139,
    "approval": 64.3750001,
    "support": 1.1679139
  },
  {
    "time_hours": 172,
    "approval_perbill": 641666668,
    "support_perbill": 11590172,
    "approval": 64.1666668,
    "support": 1.1590172
  },
  {
    "time_hours": 173,
    "approval_perbill": 639583334,
    "support_perbill": 11502202,
    "approval": 63.9583334,
    "support": 1.1502202
  },
  {
    "time_hours": 174,
    "approval_perbill": 637500001,
    "support_perbill": 11415212,
    "approval": 63.7500001,
    "support": 1.1415212
  },
  {
    "time_hours": 175,
    "approval_perbill": 635416668,
    "support_perbill": 11329185,
    "approval": 63.5416668,
    "support": 1.1329185
  },
  {
    "time_hours": 176,
    "approval_perbill": 633333335,
    "support_perbill": 11244107,
    "approval": 63.3333335,
    "support": 1.1244107
  },
  {
    "time_hours": 177,
    "approval_perbill": 631250001,
    "support_perbill": 11159960,
    "approval": 63.1250001,
    "support": 1.115996
  },
  {
    "time_hours": 178,
    "approval_perbill": 629166668,
    "support_perbill": 11076731,
    "approval": 62.9166668,
    "support": 1.1076731
  },
  {
    "time_hours": 179,
    "approval_perbill": 627083335,
    "support_perbill": 10994403,
    "approval": 62.7083335,
    "support": 1.0994403
  },
  {
    "time_hours": 180,
    "approval_perbill": 625000002,
    "support_perbill": 10912963,
    "approval": 62.5000002,
    "support": 1.0912963
  },
  {
    "time_hours": 181,
    "approval_perbill": 622916667,
    "support_perbill": 10832396,
    "approval": 62.2916667,
    "support": 1.0832396
  },
  {
    "time_hours": 182,
    "approval_perbill": 620833334,
    "support_perbill": 10752689,
    "approval": 62.0833334,
    "support": 1.0752689
  },
  {
    "time_hours": 183,
    "approval_perbill": 618750001,
    "support_perbill": 10673827,
    "approval": 61.8750001,
    "support": 1.0673827
  },
  {
    "time_hours": 184,
    "approval_perbill": 616666668,
    "support_perbill": 10595797,
    "approval": 61.6666668,
    "support": 1.0595797
  },
  {
    "time_hours": 185,
    "approval_perbill": 614583334,
    "support_perbill": 10518586,
    "approval": 61.4583334,
    "support": 1.0518586
  },
  {
    "time_hours": 186,
    "approval_perbill": 612500001,
    "support_perbill": 10442182,
    "approval": 61.2500001,
    "support": 1.0442182
  },
  {
    "time_hours": 187,
    "approval_perbill": 610416668,
    "support_perbill": 10366571,
    "approval": 61.0416668,
    "support": 1.0366571
  },
  {
    "time_hours": 188,
    "approval_perbill": 608333335,
    "support_perbill": 10291742,
    "approval": 60.8333335,
    "support": 1.0291742
  },
  {
    "time_hours": 189,
    "approval_perbill": 606250000,
    "support_perbill": 10217682,
    "approval": 60.625,
    "support": 1.0217682
  },
  {
    "time_hours": 190,
    "approval_perbill": 604166667,
    "support_perbill": 10144379,
    "approval": 60.4166667,
    "support": 1.0144379
  },
  {
    "time_hours": 191,
    "approval_perbill": 602083334,
    "support_perbill": 10071822,
    "approval": 60.2083334,
    "support": 1.0071822
  },
  {
    "time_hours": 192,
    "approval_perbill": 600000001,
    "support_perbill": 10000001,
    "approval": 60.0000001,
    "support": 1.0000001
  },
  {
    "time_hours": 193,
    "approval_perbill": 597916668,
    "support_perbill": 9928902,
    "approval": 59.7916668,
    "support": 0.9928902
  },
  {
    "time_hours": 194,
    "approval_perbill": 595833334,
    "support_perbill": 9858516,
    "approval": 59.5833334,
    "support": 0.9858516
  },
  {
    "time_hours": 195,
    "approval_perbill": 593750001,
    "support_perbill": 9788833,
    "approval": 59.3750001,
    "support": 0.9788833
  },
  {
    "time_hours": 196,
    "approval_perbill": 591666668,
    "support_perbill": 9719840,
    "approval": 59.1666668,
    "support": 0.971984
  },
  {
    "time_hours": 197,
    "approval_perbill": 589583335,
    "support_perbill": 9651529,
    "approval": 58.9583335,
    "support": 0.9651529
  },
  {
    "time_hours": 198,
    "approval_perbill": 587500001,
    "support_perbill": 9583890,
    "approval": 58.7500001,
    "support": 0.958389
  },
  {
    "time_hours": 199,
    "approval_perbill": 585416668,
    "support_perbill": 9516912,
    "approval": 58.5416668,
    "support": 0.9516912
  },
  {
    "time_hours": 200,
    "approval_perbill": 583333335,
    "support_perbill": 9450585,
    "approval": 58.3333335,
    "support": 0.9450585
  },
  {
    "time_hours": 201,
    "approval_perbill": 581250002,
    "support_perbill": 9384901,
    "approval": 58.1250002,
    "support": 0.9384901
  },
  {
    "time_hours": 202,
    "approval_perbill": 579166667,
    "support_perbill": 9319850,
    "approval": 57.9166667,
    "support": 0.931985
  },
  {
    "time_hours": 203,
    "approval_perbill": 577083334,
    "support_perbill": 9255422,
    "approval": 57.7083334,
    "support": 0.9255422
  },
  {
    "time_hours": 204,
    "approval_perbill": 575000001,
    "support_perbill": 9191610,
    "approval": 57.5000001,
    "support": 0.919161
  },
  {
    "time_hours": 205,
    "approval_perbill": 572916668,
    "support_perbill": 9128404,
    "approval": 57.2916668,
    "support": 0.9128404
  },
  {
    "time_hours": 206,
    "approval_perbill": 570833334,
    "support_perbill": 9065795,
    "approval": 57.0833334,
    "support": 0.9065795
  },
  {
    "time_hours": 207,
    "approval_perbill": 568750001,
    "support_perbill": 9003776,
    "approval": 56.8750001,
    "support": 0.9003776
  },
  {
    "time_hours": 208,
    "approval_perbill": 566666668,
    "support_perbill": 8942338,
    "approval": 56.6666668,
    "support": 0.8942338
  },
  {
    "time_hours": 209,
    "approval_perbill": 564583335,
    "support_perbill": 8881472,
    "approval": 56.4583335,
    "support": 0.8881472
  },
  {
    "time_hours": 210,
    "approval_perbill": 562500000,
    "support_perbill": 8821171,
    "approval": 56.25,
    "support": 0.8821171
  },
  {
    "time_hours": 211,
    "approval_perbill": 560416667,
    "support_perbill": 8761427,
    "approval": 56.0416667,
    "support": 0.8761427
  },
  {
    "time_hours": 212,
    "approval_perbill": 558333334,
    "support_perbill": 8702233,
    "approval": 55.8333334,
    "support": 0.8702233
  },
  {
    "time_hours": 213,
    "approval_perbill": 556250001,
    "support_perbill": 8643580,
    "approval": 55.6250001,
    "support": 0.864358
  },
  {
    "time_hours": 214,
    "approval_perbill": 554166668,
    "support_perbill": 8585461,
    "approval": 55.4166668,
    "support": 0.8585461
  },
  {
    "time_hours": 215,
    "approval_perbill": 552083334,
    "support_perbill": 8527870,
    "approval": 55.2083334,
    "support": 0.852787
  },
  {
    "time_hours": 216,
    "approval_perbill": 550000001,
    "support_perbill": 8470798,
    "approval": 55.0000001,
    "support": 0.8470798
  },
  {
    "time_hours": 217,
    "approval_perbill": 547916668,
    "support_perbill": 8414240,
    "approval": 54.7916668,
    "support": 0.841424
  },
  {
    "time_hours": 218,
    "approval_perbill": 545833335,
    "support_perbill": 8358187,
    "approval": 54.5833335,
    "support": 0.8358187
  },
  {
    "time_hours": 219,
    "approval_perbill": 543750001,
    "support_perbill": 8302634,
    "approval": 54.3750001,
    "support": 0.8302634
  },
  {
    "time_hours": 220,
    "approval_perbill": 541666668,
    "support_perbill": 8247573,
    "approval": 54.1666668,
    "support": 0.8247573
  },
  {
    "time_hours": 221,
    "approval_perbill": 539583335,
    "support_perbill": 8192999,
    "approval": 53.9583335,
    "support": 0.8192999
  },
  {
    "time_hours": 222,
    "approval_perbill": 537500002,
    "support_perbill": 8138904,
    "approval": 53.7500002,
    "support": 0.8138904
  },
  {
    "time_hours": 223,
    "approval_perbill": 535416667,
    "support_perbill": 8085283,
    "approval": 53.5416667,
    "support": 0.8085283
  },
  {
    "time_hours": 224,
    "approval_perbill": 533333334,
    "support_perbill": 8032129,
    "approval": 53.3333334,
    "support": 0.8032129
  },
  {
    "time_hours": 225,
    "approval_perbill": 531250001,
    "support_perbill": 7979436,
    "approval": 53.1250001,
    "support": 0.7979436
  },
  {
    "time_hours": 226,
    "approval_perbill": 529166668,
    "support_perbill": 7927198,
    "approval": 52.9166668,
    "support": 0.7927198
  },
  {
    "time_hours": 227,
    "approval_perbill": 527083334,
    "support_perbill": 7875409,
    "approval": 52.7083334,
    "support": 0.7875409
  },
  {
    "time_hours": 228,
    "approval_perbill": 525000001,
    "support_perbill": 7824065,
    "approval": 52.5000001,
    "support": 0.7824065
  },
  {
    "time_hours": 229,
    "approval_perbill": 522916668,
    "support_perbill": 7773157,
    "approval": 52.2916668,
    "support": 0.7773157
  },
  {
    "time_hours": 230,
    "approval_perbill": 520833335,
    "support_perbill": 7722683,
    "approval": 52.0833335,
    "support": 0.7722683
  },
  {
    "time_hours": 231,
    "approval_perbill": 518750000,
    "support_perbill": 7672634,
    "approval": 51.875,
    "support": 0.7672634
  },
  {
    "time_hours": 232,
    "approval_perbill": 516666667,
    "support_perbill": 7623008,
    "approval": 51.6666667,
    "support": 0.7623008
  },
  {
    "time_hours": 233,
    "approval_perbill": 514583334,
    "support_perbill": 7573797,
    "approval": 51.4583334,
    "support": 0.7573797
  },
  {
    "time_hours": 234,
    "approval_perbill": 512500001,
    "support_perbill": 7524998,
    "approval": 51.2500001,
    "support": 0.7524998
  },
  {
    "time_hours": 235,
    "approval_perbill": 510416668,
    "support_perbill": 7476604,
    "approval": 51.0416668,
    "support": 0.7476604
  },
  {
    "time_hours": 236,
    "approval_perbill": 508333334,
    "support_perbill": 7428611,
    "approval": 50.8333334,
    "support": 0.7428611
  },
  {
    "time_hours": 237,
    "approval_perbill": 506250001,
    "support_perbill": 7381013,
    "approval": 50.6250001,
    "support": 0.7381013
  },
  {
    "time_hours": 238,
    "approval_perbill": 504166668,
    "support_perbill": 7333807,
    "approval": 50.4166668,
    "support": 0.7333807
  },
  {
    "time_hours": 239,
    "approval_perbill": 502083335,
    "support_perbill": 7286986,
    "approval": 50.2083335,
    "support": 0.7286986
  },
  {
    "time_hours": 240,
    "approval_perbill": 500000000,
    "support_perbill": 7240547,
    "approval": 50,
    "support": 0.7240547
  },
  {
    "time_hours": 241,
    "approval_perbill": 500000000,
    "support_perbill": 7194485,
    "approval": 50,
    "support": 0.7194485
  },
  {
    "time_hours": 242,
    "approval_perbill": 500000000,
    "support_perbill": 7148795,
    "approval": 50,
    "support": 0.7148795
  },
  {
    "time_hours": 243,
    "approval_perbill": 500000000,
    "support_perbill": 7103472,
    "approval": 50,
    "support": 0.7103472
  },
  {
    "time_hours": 244,
    "approval_perbill": 500000000,
    "support_perbill": 7058513,
    "approval": 50,
    "support": 0.7058513
  },
  {
    "time_hours": 245,
    "approval_perbill": 500000000,
    "support_perbill": 7013913,
    "approval": 50,
    "support": 0.7013913
  },
  {
    "time_hours": 246,
    "approval_perbill": 500000000,
    "support_perbill": 6969667,
    "approval": 50,
    "support": 0.6969667
  },
  {
    "time_hours": 247,
    "approval_perbill": 500000000,
    "support_perbill": 6925772,
    "approval": 50,
    "support": 0.6925772
  },
  {
    "time_hours": 248,
    "approval_perbill": 500000000,
    "support_perbill": 6882223,
    "approval": 50,
    "support": 0.6882223
  },
  {
    "time_hours": 249,
    "approval_perbill": 500000000,
    "support_perbill": 6839016,
    "approval": 50,
    "support": 0.6839016
  },
  {
    "time_hours": 250,
    "approval_perbill": 500000000,
    "support_perbill": 6796148,
    "approval": 50,
    "support": 0.6796148
  },
  {
    "time_hours": 251,
    "approval_perbill": 500000000,
    "support_perbill": 6753614,
    "approval": 50,
    "support": 0.6753614
  },
  {
    "time_hours": 252,
    "approval_perbill": 500000000,
    "support_perbill": 6711409,
    "approval": 50,
    "support": 0.6711409
  },
  {
    "time_hours": 253,
    "approval_perbill": 500000000,
    "support_perbill": 6669532,
    "approval": 50,
    "support": 0.6669532
  },
  {
    "time_hours": 254,
    "approval_perbill": 500000000,
    "support_perbill": 6627977,
    "approval": 50,
    "support": 0.6627977
  },
  {
    "time_hours": 255,
    "approval_perbill": 500000000,
    "support_perbill": 6586741,
    "approval": 50,
    "support": 0.6586741
  },
  {
    "time_hours": 256,
    "approval_perbill": 500000000,
    "support_perbill": 6545821,
    "approval": 50,
    "support": 0.6545821
  },
  {
    "time_hours": 257,
    "approval_perbill": 500000000,
    "support_perbill": 6505212,
    "approval": 50,
    "support": 0.6505212
  },
  {
    "time_hours": 258,
    "approval_perbill": 500000000,
    "support_perbill": 6464912,
    "approval": 50,
    "support": 0.6464912
  },
  {
    "time_hours": 259,
    "approval_perbill": 500000000,
    "support_perbill": 6424916,
    "approval": 50,
    "support": 0.6424916
  },
  {
    "time_hours": 260,
    "approval_perbill": 500000000,
    "support_perbill": 6385221,
    "approval": 50,
    "support": 0.6385221
  },
  {
    "time_hours": 261,
    "approval_perbill": 500000000,
    "support_perbill": 6345824,
    "approval": 50,
    "support": 0.6345824
  },
  {
    "time_hours": 262,
    "approval_perbill": 500000000,
    "support_perbill": 6306722,
    "approval": 50,
    "support": 0.6306722
  },
  {
    "time_hours": 263,
    "approval_perbill": 500000000,
    "support_perbill": 6267911,
    "approval": 50,
    "support": 0.6267911
  },
  {
    "time_hours": 264,
    "approval_perbill": 500000000,
    "support_perbill": 6229388,
    "approval": 50,
    "support": 0.6229388
  },
  {
    "time_hours": 265,
    "approval_perbill": 500000000,
    "support_perbill": 6191150,
    "approval": 50,
    "support": 0.619115
  },
  {
    "time_hours": 266,
    "approval_perbill": 500000000,
    "support_perbill": 6153193,
    "approval": 50,
    "support": 0.6153193
  },
  {
    "time_hours": 267,
    "approval_perbill": 500000000,
    "support_perbill": 6115515,
    "approval": 50,
    "support": 0.6115515
  },
  {
    "time_hours": 268,
    "approval_perbill": 500000000,
    "support_perbill": 6078113,
    "approval": 50,
    "support": 0.6078113
  },
  {
    "time_hours": 269,
    "approval_perbill": 500000000,
    "support_perbill": 6040983,
    "approval": 50,
    "support": 0.6040983
  },
  {
    "time_hours": 270,
    "approval_perbill": 500000000,
    "support_perbill": 6004122,
    "approval": 50,
    "support": 0.6004122
  },
  {
    "time_hours": 271,
    "approval_perbill": 500000000,
    "support_perbill": 5967528,
    "approval": 50,
    "support": 0.5967528
  },
  {
    "time_hours": 272,
    "approval_perbill": 500000000,
    "support_perbill": 5931198,
    "approval": 50,
    "support": 0.5931198
  },
  {
    "time_hours": 273,
    "approval_perbill": 500000000,
    "support_perbill": 5895129,
    "approval": 50,
    "support": 0.5895129
  },
  {
    "time_hours": 274,
    "approval_perbill": 500000000,
    "support_perbill": 5859317,
    "approval": 50,
    "support": 0.5859317
  },
  {
    "time_hours": 275,
    "approval_perbill": 500000000,
    "support_perbill": 5823762,
    "approval": 50,
    "support": 0.5823762
  },
  {
    "time_hours": 276,
    "approval_perbill": 500000000,
    "support_perbill": 5788458,
    "approval": 50,
    "support": 0.5788458
  },
  {
    "time_hours": 277,
    "approval_perbill": 500000000,
    "support_perbill": 5753405,
    "approval": 50,
    "support": 0.5753405
  },
  {
    "time_hours": 278,
    "approval_perbill": 500000000,
    "support_perbill": 5718598,
    "approval": 50,
    "support": 0.5718598
  },
  {
    "time_hours": 279,
    "approval_perbill": 500000000,
    "support_perbill": 5684037,
    "approval": 50,
    "support": 0.5684037
  },
  {
    "time_hours": 280,
    "approval_perbill": 500000000,
    "support_perbill": 5649718,
    "approval": 50,
    "support": 0.5649718
  },
  {
    "time_hours": 281,
    "approval_perbill": 500000000,
    "support_perbill": 5615638,
    "approval": 50,
    "support": 0.5615638
  },
  {
    "time_hours": 282,
    "approval_perbill": 500000000,
    "support_perbill": 5581795,
    "approval": 50,
    "support": 0.5581795
  },
  {
    "time_hours": 283,
    "approval_perbill": 500000000,
    "support_perbill": 5548186,
    "approval": 50,
    "support": 0.5548186
  },
  {
    "time_hours": 284,
    "approval_perbill": 500000000,
    "support_perbill": 5514810,
    "approval": 50,
    "support": 0.551481
  },
  {
    "time_hours": 285,
    "approval_perbill": 500000000,
    "support_perbill": 5481664,
    "approval": 50,
    "support": 0.5481664
  },
  {
    "time_hours": 286,
    "approval_perbill": 500000000,
    "support_perbill": 5448745,
    "approval": 50,
    "support": 0.5448745
  },
  {
    "time_hours": 287,
    "approval_perbill": 500000000,
    "support_perbill": 5416051,
    "approval": 50,
    "support": 0.5416051
  },
  {
    "time_hours": 288,
    "approval_perbill": 500000000,
    "support_perbill": 5383580,
    "approval": 50,
    "support": 0.538358
  },
  {
    "time_hours": 289,
    "approval_perbill": 500000000,
    "support_perbill": 5351329,
    "approval": 50,
    "support": 0.5351329
  },
  {
    "time_hours": 290,
    "approval_perbill": 500000000,
    "support_perbill": 5319297,
    "approval": 50,
    "support": 0.5319297
  },
  {
    "time_hours": 291,
    "approval_perbill": 500000000,
    "support_perbill": 5287481,
    "approval": 50,
    "support": 0.5287481
  },
  {
    "time_hours": 292,
    "approval_perbill": 500000000,
    "support_perbill": 5255878,
    "approval": 50,
    "support": 0.5255878
  },
  {
    "time_hours": 293,
    "approval_perbill": 500000000,
    "support_perbill": 5224487,
    "approval": 50,
    "support": 0.5224487
  },
  {
    "time_hours": 294,
    "approval_perbill": 500000000,
    "support_perbill": 5193306,
    "approval": 50,
    "support": 0.5193306
  },
  {
    "time_hours": 295,
    "approval_perbill": 500000000,
    "support_perbill": 5162333,
    "approval": 50,
    "support": 0.5162333
  },
  {
    "time_hours": 296,
    "approval_perbill": 500000000,
    "support_perbill": 5131565,
    "approval": 50,
    "support": 0.5131565
  },
  {
    "time_hours": 297,
    "approval_perbill": 500000000,
    "support_perbill": 5101000,
    "approval": 50,
    "support": 0.5101
  },
  {
    "time_hours": 298,
    "approval_perbill": 500000000,
    "support_perbill": 5070636,
    "approval": 50,
    "support": 0.5070636
  },
  {
    "time_hours": 299,
    "approval_perbill": 500000000,
    "support_perbill": 5040472,
    "approval": 50,
    "support": 0.5040472
  },
  {
    "time_hours": 300,
    "approval_perbill": 500000000,
    "support_perbill": 5010506,
    "approval": 50,
    "support": 0.5010506
  },
  {
    "time_hours": 301,
    "approval_perbill": 500000000,
    "support_perbill": 4980735,
    "approval": 50,
    "support": 0.4980735
  },
  {
    "time_hours": 302,
    "approval_perbill": 500000000,
    "support_perbill": 4951157,
    "approval": 50,
    "support": 0.4951157
  },
  {
    "time_hours": 303,
    "approval_perbill": 500000000,
    "support_perbill": 4921772,
    "approval": 50,
    "support": 0.4921772
  },
  {
    "time_hours": 304,
    "approval_perbill": 500000000,
    "support_perbill": 4892576,
    "approval": 50,
    "support": 0.4892576
  },
  {
    "time_hours": 305,
    "approval_perbill": 500000000,
    "support_perbill": 4863568,
    "approval": 50,
    "support": 0.4863568
  },
  {
    "time_hours": 306,
    "approval_perbill": 500000000,
    "support_perbill": 4834747,
    "approval": 50,
    "support": 0.4834747
  },
  {
    "time_hours": 307,
    "approval_perbill": 500000000,
    "support_perbill": 4806110,
    "approval": 50,
    "support": 0.480611
  },
  {
    "time_hours": 308,
    "approval_perbill": 500000000,
    "support_perbill": 4777655,
    "approval": 50,
    "support": 0.4777655
  },
  {
    "time_hours": 309,
    "approval_perbill": 500000000,
    "support_perbill": 4749382,
    "approval": 50,
    "support": 0.4749382
  },
  {
    "time_hours": 310,
    "approval_perbill": 500000000,
    "support_perbill": 4721287,
    "approval": 50,
    "support": 0.4721287
  },
  {
    "time_hours": 311,
    "approval_perbill": 500000000,
    "support_perbill": 4693371,
    "approval": 50,
    "support": 0.4693371
  },
  {
    "time_hours": 312,
    "approval_perbill": 500000000,
    "support_perbill": 4665630,
    "approval": 50,
    "support": 0.466563
  },
  {
    "time_hours": 313,
    "approval_perbill": 500000000,
    "support_perbill": 4638063,
    "approval": 50,
    "support": 0.4638063
  },
  {
    "time_hours": 314,
    "approval_perbill": 500000000,
    "support_perbill": 4610669,
    "approval": 50,
    "support": 0.4610669
  },
  {
    "time_hours": 315,
    "approval_perbill": 500000000,
    "support_perbill": 4583446,
    "approval": 50,
    "support": 0.4583446
  },
  {
    "time_hours": 316,
    "approval_perbill": 500000000,
    "support_perbill": 4556392,
    "approval": 50,
    "support": 0.4556392
  },
  {
    "time_hours": 317,
    "approval_perbill": 500000000,
    "support_perbill": 4529505,
    "approval": 50,
    "support": 0.4529505
  },
  {
    "time_hours": 318,
    "approval_perbill": 500000000,
    "support_perbill": 4502785,
    "approval": 50,
    "support": 0.4502785
  },
  {
    "time_hours": 319,
    "approval_perbill": 500000000,
    "support_perbill": 4476230,
    "approval": 50,
    "support": 0.447623
  },
  {
    "time_hours": 320,
    "approval_perbill": 500000000,
    "support_perbill": 4449838,
    "approval": 50,
    "support": 0.4449838
  },
  {
    "time_hours": 321,
    "approval_perbill": 500000000,
    "support_perbill": 4423608,
    "approval": 50,
    "support": 0.4423608
  },
  {
    "time_hours": 322,
    "approval_perbill": 500000000,
    "support_perbill": 4397537,
    "approval": 50,
    "support": 0.4397537
  },
  {
    "time_hours": 323,
    "approval_perbill": 500000000,
    "support_perbill": 4371626,
    "approval": 50,
    "support": 0.4371626
  },
  {
    "time_hours": 324,
    "approval_perbill": 500000000,
    "support_perbill": 4345871,
    "approval": 50,
    "support": 0.4345871
  },
  {
    "time_hours": 325,
    "approval_perbill": 500000000,
    "support_perbill": 4320273,
    "approval": 50,
    "support": 0.4320273
  },
  {
    "time_hours": 326,
    "approval_perbill": 500000000,
    "support_perbill": 4294829,
    "approval": 50,
    "support": 0.4294829
  },
  {
    "time_hours": 327,
    "approval_perbill": 500000000,
    "support_perbill": 4269538,
    "approval": 50,
    "support": 0.4269538
  },
  {
    "time_hours": 328,
    "approval_perbill": 500000000,
    "support_perbill": 4244398,
    "approval": 50,
    "support": 0.4244398
  },
  {
    "time_hours": 329,
    "approval_perbill": 500000000,
    "support_perbill": 4219409,
    "approval": 50,
    "support": 0.4219409
  },
  {
    "time_hours": 330,
    "approval_perbill": 500000000,
    "support_perbill": 4194569,
    "approval": 50,
    "support": 0.4194569
  },
  {
    "time_hours": 331,
    "approval_perbill": 500000000,
    "support_perbill": 4169876,
    "approval": 50,
    "support": 0.4169876
  },
  {
    "time_hours": 332,
    "approval_perbill": 500000000,
    "support_perbill": 4145330,
    "approval": 50,
    "support": 0.414533
  },
  {
    "time_hours": 333,
    "approval_perbill": 500000000,
    "support_perbill": 4120929,
    "approval": 50,
    "support": 0.4120929
  },
  {
    "time_hours": 334,
    "approval_perbill": 500000000,
    "support_perbill": 4096672,
    "approval": 50,
    "support": 0.4096672
  },
  {
    "time_hours": 335,
    "approval_perbill": 500000000,
    "support_perbill": 4072557,
    "approval": 50,
    "support": 0.4072557
  },
  {
    "time_hours": 336,
    "approval_perbill": 500000000,
    "support_perbill": 4048583,
    "approval": 50,
    "support": 0.4048583
  },
  {
    "time_hours": 337,
    "approval_perbill": 500000000,
    "support_perbill": 4024749,
    "approval": 50,
    "support": 0.4024749
  },
  {
    "time_hours": 338,
    "approval_perbill": 500000000,
    "support_perbill": 4001054,
    "approval": 50,
    "support": 0.4001054
  },
  {
    "time_hours": 339,
    "approval_perbill": 500000000,
    "support_perbill": 3977496,
    "approval": 50,
    "support": 0.3977496
  },
  {
    "time_hours": 340,
    "approval_perbill": 500000000,
    "support_perbill": 3954075,
    "approval": 50,
    "support": 0.3954075
  },
  {
    "time_hours": 341,
    "approval_perbill": 500000000,
    "support_perbill": 3930789,
    "approval": 50,
    "support": 0.3930789
  },
  {
    "time_hours": 342,
    "approval_perbill": 500000000,
    "support_perbill": 3907637,
    "approval": 50,
    "support": 0.3907637
  },
  {
    "time_hours": 343,
    "approval_perbill": 500000000,
    "support_perbill": 3884618,
    "approval": 50,
    "support": 0.3884618
  },
  {
    "time_hours": 344,
    "approval_perbill": 500000000,
    "support_perbill": 3861731,
    "approval": 50,
    "support": 0.3861731
  },
  {
    "time_hours": 345,
    "approval_perbill": 500000000,
    "support_perbill": 3838974,
    "approval": 50,
    "support": 0.3838974
  },
  {
    "time_hours": 346,
    "approval_perbill": 500000000,
    "support_perbill": 3816347,
    "approval": 50,
    "support": 0.3816347
  },
  {
    "time_hours": 347,
    "approval_perbill": 500000000,
    "support_perbill": 3793848,
    "approval": 50,
    "support": 0.3793848
  },
  {
    "time_hours": 348,
    "approval_perbill": 500000000,
    "support_perbill": 3771476,
    "approval": 50,
    "support": 0.3771476
  },
  {
    "time_hours": 349,
    "approval_perbill": 500000000,
    "support_perbill": 3749231,
    "approval": 50,
    "support": 0.3749231
  },
  {
    "time_hours": 350,
    "approval_perbill": 500000000,
    "support_perbill": 3727110,
    "approval": 50,
    "support": 0.372711
  },
  {
    "time_hours": 351,
    "approval_perbill": 500000000,
    "support_perbill": 3705114,
    "approval": 50,
    "support": 0.3705114
  },
  {
    "time_hours": 352,
    "approval_perbill": 500000000,
    "support_perbill": 3683241,
    "approval": 50,
    "support": 0.3683241
  },
  {
    "time_hours": 353,
    "approval_perbill": 500000000,
    "support_perbill": 3661490,
    "approval": 50,
    "support": 0.366149
  },
  {
    "time_hours": 354,
    "approval_perbill": 500000000,
    "support_perbill": 3639860,
    "approval": 50,
    "support": 0.363986
  },
  {
    "time_hours": 355,
    "approval_perbill": 500000000,
    "support_perbill": 3618349,
    "approval": 50,
    "support": 0.3618349
  },
  {
    "time_hours": 356,
    "approval_perbill": 500000000,
    "support_perbill": 3596958,
    "approval": 50,
    "support": 0.3596958
  },
  {
    "time_hours": 357,
    "approval_perbill": 500000000,
    "support_perbill": 3575685,
    "approval": 50,
    "support": 0.3575685
  },
  {
    "time_hours": 358,
    "approval_perbill": 500000000,
    "support_perbill": 3554529,
    "approval": 50,
    "support": 0.3554529
  },
  {
    "time_hours": 359,
    "approval_perbill": 500000000,
    "support_perbill": 3533489,
    "approval": 50,
    "support": 0.3533489
  },
  {
    "time_hours": 360,
    "approval_perbill": 500000000,
    "support_perbill": 3512564,
    "approval": 50,
    "support": 0.3512564
  },
  {
    "time_hours": 361,
    "approval_perbill": 500000000,
    "support_perbill": 3491753,
    "approval": 50,
    "support": 0.3491753
  },
  {
    "time_hours": 362,
    "approval_perbill": 500000000,
    "support_perbill": 3471056,
    "approval": 50,
    "support": 0.3471056
  },
  {
    "time_hours": 363,
    "approval_perbill": 500000000,
    "support_perbill": 3450470,
    "approval": 50,
    "support": 0.345047
  },
  {
    "time_hours": 364,
    "approval_perbill": 500000000,
    "support_perbill": 3429997,
    "approval": 50,
    "support": 0.3429997
  },
  {
    "time_hours": 365,
    "approval_perbill": 500000000,
    "support_perbill": 3409633,
    "approval": 50,
    "support": 0.3409633
  },
  {
    "time_hours": 366,
    "approval_perbill": 500000000,
    "support_perbill": 3389380,
    "approval": 50,
    "support": 0.338938
  },
  {
    "time_hours": 367,
    "approval_perbill": 500000000,
    "support_perbill": 3369235,
    "approval": 50,
    "support": 0.3369235
  },
  {
    "time_hours": 368,
    "approval_perbill": 500000000,
    "support_perbill": 3349198,
    "approval": 50,
    "support": 0.3349198
  },
  {
    "time_hours": 369,
    "approval_perbill": 500000000,
    "support_perbill": 3329268,
    "approval": 50,
    "support": 0.3329268
  },
  {
    "time_hours": 370,
    "approval_perbill": 500000000,
    "support_perbill": 3309444,
    "approval": 50,
    "support": 0.3309444
  },
  {
    "time_hours": 371,
    "approval_perbill": 500000000,
    "support_perbill": 3289725,
    "approval": 50,
    "support": 0.3289725
  },
  {
    "time_hours": 372,
    "approval_perbill": 500000000,
    "support_perbill": 3270111,
    "approval": 50,
    "support": 0.3270111
  },
  {
    "time_hours": 373,
    "approval_perbill": 500000000,
    "support_perbill": 3250600,
    "approval": 50,
    "support": 0.32506
  },
  {
    "time_hours": 374,
    "approval_perbill": 500000000,
    "support_perbill": 3231193,
    "approval": 50,
    "support": 0.3231193
  },
  {
    "time_hours": 375,
    "approval_perbill": 500000000,
    "support_perbill": 3211887,
    "approval": 50,
    "support": 0.3211887
  },
  {
    "time_hours": 376,
    "approval_perbill": 500000000,
    "support_perbill": 3192682,
    "approval": 50,
    "support": 0.3192682
  },
  {
    "time_hours": 377,
    "approval_perbill": 500000000,
    "support_perbill": 3173578,
    "approval": 50,
    "support": 0.3173578
  },
  {
    "time_hours": 378,
    "approval_perbill": 500000000,
    "support_perbill": 3154574,
    "approval": 50,
    "support": 0.3154574
  },
  {
    "time_hours": 379,
    "approval_perbill": 500000000,
    "support_perbill": 3135668,
    "approval": 50,
    "support": 0.3135668
  },
  {
    "time_hours": 380,
    "approval_perbill": 500000000,
    "support_perbill": 3116861,
    "approval": 50,
    "support": 0.3116861
  },
  {
    "time_hours": 381,
    "approval_perbill": 500000000,
    "support_perbill": 3098150,
    "approval": 50,
    "support": 0.309815
  },
  {
    "time_hours": 382,
    "approval_perbill": 500000000,
    "support_perbill": 3079537,
    "approval": 50,
    "support": 0.3079537
  },
  {
    "time_hours": 383,
    "approval_perbill": 500000000,
    "support_perbill": 3061019,
    "approval": 50,
    "support": 0.3061019
  },
  {
    "time_hours": 384,
    "approval_perbill": 500000000,
    "support_perbill": 3042596,
    "approval": 50,
    "support": 0.3042596
  },
  {
    "time_hours": 385,
    "approval_perbill": 500000000,
    "support_perbill": 3024268,
    "approval": 50,
    "support": 0.3024268
  },
  {
    "time_hours": 386,
    "approval_perbill": 500000000,
    "support_perbill": 3006033,
    "approval": 50,
    "support": 0.3006033
  },
  {
    "time_hours": 387,
    "approval_perbill": 500000000,
    "support_perbill": 2987891,
    "approval": 50,
    "support": 0.2987891
  },
  {
    "time_hours": 388,
    "approval_perbill": 500000000,
    "support_perbill": 2969841,
    "approval": 50,
    "support": 0.2969841
  },
  {
    "time_hours": 389,
    "approval_perbill": 500000000,
    "support_perbill": 2951883,
    "approval": 50,
    "support": 0.2951883
  },
  {
    "time_hours": 390,
    "approval_perbill": 500000000,
    "support_perbill": 2934016,
    "approval": 50,
    "support": 0.2934016
  },
  {
    "time_hours": 391,
    "approval_perbill": 500000000,
    "support_perbill": 2916238,
    "approval": 50,
    "support": 0.2916238
  },
  {
    "time_hours": 392,
    "approval_perbill": 500000000,
    "support_perbill": 2898550,
    "approval": 50,
    "support": 0.289855
  },
  {
    "time_hours": 393,
    "approval_perbill": 500000000,
    "support_perbill": 2880951,
    "approval": 50,
    "support": 0.2880951
  },
  {
    "time_hours": 394,
    "approval_perbill": 500000000,
    "support_perbill": 2863440,
    "approval": 50,
    "support": 0.286344
  },
  {
    "time_hours": 395,
    "approval_perbill": 500000000,
    "support_perbill": 2846017,
    "approval": 50,
    "support": 0.2846017
  },
  {
    "time_hours": 396,
    "approval_perbill": 500000000,
    "support_perbill": 2828680,
    "approval": 50,
    "support": 0.282868
  },
  {
    "time_hours": 397,
    "approval_perbill": 500000000,
    "support_perbill": 2811429,
    "approval": 50,
    "support": 0.2811429
  },
  {
    "time_hours": 398,
    "approval_perbill": 500000000,
    "support_perbill": 2794264,
    "approval": 50,
    "support": 0.2794264
  },
  {
    "time_hours": 399,
    "approval_perbill": 500000000,
    "support_perbill": 2777184,
    "approval": 50,
    "support": 0.2777184
  },
  {
    "time_hours": 400,
    "approval_perbill": 500000000,
    "support_perbill": 2760188,
    "approval": 50,
    "support": 0.2760188
  },
  {
    "time_hours": 401,
    "approval_perbill": 500000000,
    "support_perbill": 2743276,
    "approval": 50,
    "support": 0.2743276
  },
  {
    "time_hours": 402,
    "approval_perbill": 500000000,
    "support_perbill": 2726446,
    "approval": 50,
    "support": 0.2726446
  },
  {
    "time_hours": 403,
    "approval_perbill": 500000000,
    "support_perbill": 2709699,
    "approval": 50,
    "support": 0.2709699
  },
  {
    "time_hours": 404,
    "approval_perbill": 500000000,
    "support_perbill": 2693034,
    "approval": 50,
    "support": 0.2693034
  },
  {
    "time_hours": 405,
    "approval_perbill": 500000000,
    "support_perbill": 2676450,
    "approval": 50,
    "support": 0.267645
  },
  {
    "time_hours": 406,
    "approval_perbill": 500000000,
    "support_perbill": 2659946,
    "approval": 50,
    "support": 0.2659946
  },
  {
    "time_hours": 407,
    "approval_perbill": 500000000,
    "support_perbill": 2643523,
    "approval": 50,
    "support": 0.2643523
  },
  {
    "time_hours": 408,
    "approval_perbill": 500000000,
    "support_perbill": 2627179,
    "approval": 50,
    "support": 0.2627179
  },
  {
    "time_hours": 409,
    "approval_perbill": 500000000,
    "support_perbill": 2610914,
    "approval": 50,
    "support": 0.2610914
  },
  {
    "time_hours": 410,
    "approval_perbill": 500000000,
    "support_perbill": 2594727,
    "approval": 50,
    "support": 0.2594727
  },
  {
    "time_hours": 411,
    "approval_perbill": 500000000,
    "support_perbill": 2578618,
    "approval": 50,
    "support": 0.2578618
  },
  {
    "time_hours": 412,
    "approval_perbill": 500000000,
    "support_perbill": 2562586,
    "approval": 50,
    "support": 0.2562586
  },
  {
    "time_hours": 413,
    "approval_perbill": 500000000,
    "support_perbill": 2546630,
    "approval": 50,
    "support": 0.254663
  },
  {
    "time_hours": 414,
    "approval_perbill": 500000000,
    "support_perbill": 2530751,
    "approval": 50,
    "support": 0.2530751
  },
  {
    "time_hours": 415,
    "approval_perbill": 500000000,
    "support_perbill": 2514947,
    "approval": 50,
    "support": 0.2514947
  },
  {
    "time_hours": 416,
    "approval_perbill": 500000000,
    "support_perbill": 2499219,
    "approval": 50,
    "support": 0.2499219
  },
  {
    "time_hours": 417,
    "approval_perbill": 500000000,
    "support_perbill": 2483564,
    "approval": 50,
    "support": 0.2483564
  },
  {
    "time_hours": 418,
    "approval_perbill": 500000000,
    "support_perbill": 2467984,
    "approval": 50,
    "support": 0.2467984
  },
  {
    "time_hours": 419,
    "approval_perbill": 500000000,
    "support_perbill": 2452477,
    "approval": 50,
    "support": 0.2452477
  },
  {
    "time_hours": 420,
    "approval_perbill": 500000000,
    "support_perbill": 2437043,
    "approval": 50,
    "support": 0.2437043
  },
  {
    "time_hours": 421,
    "approval_perbill": 500000000,
    "support_perbill": 2421681,
    "approval": 50,
    "support": 0.2421681
  },
  {
    "time_hours": 422,
    "approval_perbill": 500000000,
    "support_perbill": 2406391,
    "approval": 50,
    "support": 0.2406391
  },
  {
    "time_hours": 423,
    "approval_perbill": 500000000,
    "support_perbill": 2391172,
    "approval": 50,
    "support": 0.2391172
  },
  {
    "time_hours": 424,
    "approval_perbill": 500000000,
    "support_perbill": 2376025,
    "approval": 50,
    "support": 0.2376025
  },
  {
    "time_hours": 425,
    "approval_perbill": 500000000,
    "support_perbill": 2360947,
    "approval": 50,
    "support": 0.2360947
  },
  {
    "time_hours": 426,
    "approval_perbill": 500000000,
    "support_perbill": 2345940,
    "approval": 50,
    "support": 0.234594
  },
  {
    "time_hours": 427,
    "approval_perbill": 500000000,
    "support_perbill": 2331002,
    "approval": 50,
    "support": 0.2331002
  },
  {
    "time_hours": 428,
    "approval_perbill": 500000000,
    "support_perbill": 2316133,
    "approval": 50,
    "support": 0.2316133
  },
  {
    "time_hours": 429,
    "approval_perbill": 500000000,
    "support_perbill": 2301332,
    "approval": 50,
    "support": 0.2301332
  },
  {
    "time_hours": 430,
    "approval_perbill": 500000000,
    "support_perbill": 2286599,
    "approval": 50,
    "support": 0.2286599
  },
  {
    "time_hours": 431,
    "approval_perbill": 500000000,
    "support_perbill": 2271934,
    "approval": 50,
    "support": 0.2271934
  },
  {
    "time_hours": 432,
    "approval_perbill": 500000000,
    "support_perbill": 2257336,
    "approval": 50,
    "support": 0.2257336
  },
  {
    "time_hours": 433,
    "approval_perbill": 500000000,
    "support_perbill": 2242804,
    "approval": 50,
    "support": 0.2242804
  },
  {
    "time_hours": 434,
    "approval_perbill": 500000000,
    "support_perbill": 2228339,
    "approval": 50,
    "support": 0.2228339
  },
  {
    "time_hours": 435,
    "approval_perbill": 500000000,
    "support_perbill": 2213939,
    "approval": 50,
    "support": 0.2213939
  },
  {
    "time_hours": 436,
    "approval_perbill": 500000000,
    "support_perbill": 2199604,
    "approval": 50,
    "support": 0.2199604
  },
  {
    "time_hours": 437,
    "approval_perbill": 500000000,
    "support_perbill": 2185335,
    "approval": 50,
    "support": 0.2185335
  },
  {
    "time_hours": 438,
    "approval_perbill": 500000000,
    "support_perbill": 2171129,
    "approval": 50,
    "support": 0.2171129
  },
  {
    "time_hours": 439,
    "approval_perbill": 500000000,
    "support_perbill": 2156988,
    "approval": 50,
    "support": 0.2156988
  },
  {
    "time_hours": 440,
    "approval_perbill": 500000000,
    "support_perbill": 2142909,
    "approval": 50,
    "support": 0.2142909
  },
  {
    "time_hours": 441,
    "approval_perbill": 500000000,
    "support_perbill": 2128894,
    "approval": 50,
    "support": 0.2128894
  },
  {
    "time_hours": 442,
    "approval_perbill": 500000000,
    "support_perbill": 2114942,
    "approval": 50,
    "support": 0.2114942
  },
  {
    "time_hours": 443,
    "approval_perbill": 500000000,
    "support_perbill": 2101052,
    "approval": 50,
    "support": 0.2101052
  },
  {
    "time_hours": 444,
    "approval_perbill": 500000000,
    "support_perbill": 2087224,
    "approval": 50,
    "support": 0.2087224
  },
  {
    "time_hours": 445,
    "approval_perbill": 500000000,
    "support_perbill": 2073457,
    "approval": 50,
    "support": 0.2073457
  },
  {
    "time_hours": 446,
    "approval_perbill": 500000000,
    "support_perbill": 2059751,
    "approval": 50,
    "support": 0.2059751
  },
  {
    "time_hours": 447,
    "approval_perbill": 500000000,
    "support_perbill": 2046105,
    "approval": 50,
    "support": 0.2046105
  },
  {
    "time_hours": 448,
    "approval_perbill": 500000000,
    "support_perbill": 2032520,
    "approval": 50,
    "support": 0.203252
  },
  {
    "time_hours": 449,
    "approval_perbill": 500000000,
    "support_perbill": 2018994,
    "approval": 50,
    "support": 0.2018994
  },
  {
    "time_hours": 450,
    "approval_perbill": 500000000,
    "support_perbill": 2005528,
    "approval": 50,
    "support": 0.2005528
  },
  {
    "time_hours": 451,
    "approval_perbill": 500000000,
    "support_perbill": 1992121,
    "approval": 50,
    "support": 0.1992121
  },
  {
    "time_hours": 452,
    "approval_perbill": 500000000,
    "support_perbill": 1978773,
    "approval": 50,
    "support": 0.1978773
  },
  {
    "time_hours": 453,
    "approval_perbill": 500000000,
    "support_perbill": 1965482,
    "approval": 50,
    "support": 0.1965482
  },
  {
    "time_hours": 454,
    "approval_perbill": 500000000,
    "support_perbill": 1952250,
    "approval": 50,
    "support": 0.195225
  },
  {
    "time_hours": 455,
    "approval_perbill": 500000000,
    "support_perbill": 1939075,
    "approval": 50,
    "support": 0.1939075
  },
  {
    "time_hours": 456,
    "approval_perbill": 500000000,
    "support_perbill": 1925957,
    "approval": 50,
    "support": 0.1925957
  },
  {
    "time_hours": 457,
    "approval_perbill": 500000000,
    "support_perbill": 1912896,
    "approval": 50,
    "support": 0.1912896
  },
  {
    "time_hours": 458,
    "approval_perbill": 500000000,
    "support_perbill": 1899891,
    "approval": 50,
    "support": 0.1899891
  },
  {
    "time_hours": 459,
    "approval_perbill": 500000000,
    "support_perbill": 1886942,
    "approval": 50,
    "support": 0.1886942
  },
  {
    "time_hours": 460,
    "approval_perbill": 500000000,
    "support_perbill": 1874049,
    "approval": 50,
    "support": 0.1874049
  },
  {
    "time_hours": 461,
    "approval_perbill": 500000000,
    "support_perbill": 1861211,
    "approval": 50,
    "support": 0.1861211
  },
  {
    "time_hours": 462,
    "approval_perbill": 500000000,
    "support_perbill": 1848428,
    "approval": 50,
    "support": 0.1848428
  },
  {
    "time_hours": 463,
    "approval_perbill": 500000000,
    "support_perbill": 1835700,
    "approval": 50,
    "support": 0.18357
  },
  {
    "time_hours": 464,
    "approval_perbill": 500000000,
    "support_perbill": 1823026,
    "approval": 50,
    "support": 0.1823026
  },
  {
    "time_hours": 465,
    "approval_perbill": 500000000,
    "support_perbill": 1810405,
    "approval": 50,
    "support": 0.1810405
  },
  {
    "time_hours": 466,
    "approval_perbill": 500000000,
    "support_perbill": 1797839,
    "approval": 50,
    "support": 0.1797839
  },
  {
    "time_hours": 467,
    "approval_perbill": 500000000,
    "support_perbill": 1785325,
    "approval": 50,
    "support": 0.1785325
  },
  {
    "time_hours": 468,
    "approval_perbill": 500000000,
    "support_perbill": 1772864,
    "approval": 50,
    "support": 0.1772864
  },
  {
    "time_hours": 469,
    "approval_perbill": 500000000,
    "support_perbill": 1760456,
    "approval": 50,
    "support": 0.1760456
  },
  {
    "time_hours": 470,
    "approval_perbill": 500000000,
    "support_perbill": 1748100,
    "approval": 50,
    "support": 0.17481
  },
  {
    "time_hours": 471,
    "approval_perbill": 500000000,
    "support_perbill": 1735796,
    "approval": 50,
    "support": 0.1735796
  },
  {
    "time_hours": 472,
    "approval_perbill": 500000000,
    "support_perbill": 1723543,
    "approval": 50,
    "support": 0.1723543
  },
  {
    "time_hours": 473,
    "approval_perbill": 500000000,
    "support_perbill": 1711342,
    "approval": 50,
    "support": 0.1711342
  },
  {
    "time_hours": 474,
    "approval_perbill": 500000000,
    "support_perbill": 1699191,
    "approval": 50,
    "support": 0.1699191
  },
  {
    "time_hours": 475,
    "approval_perbill": 500000000,
    "support_perbill": 1687091,
    "approval": 50,
    "support": 0.1687091
  },
  {
    "time_hours": 476,
    "approval_perbill": 500000000,
    "support_perbill": 1675041,
    "approval": 50,
    "support": 0.1675041
  },
  {
    "time_hours": 477,
    "approval_perbill": 500000000,
    "support_perbill": 1663042,
    "approval": 50,
    "support": 0.1663042
  },
  {
    "time_hours": 478,
    "approval_perbill": 500000000,
    "support_perbill": 1651091,
    "approval": 50,
    "support": 0.1651091
  },
  {
    "time_hours": 479,
    "approval_perbill": 500000000,
    "support_perbill": 1639191,
    "approval": 50,
    "support": 0.1639191
  },
  {
    "time_hours": 480,
    "approval_perbill": 500000000,
    "support_perbill": 1627339,
    "approval": 50,
    "support": 0.1627339
  },
  {
    "time_hours": 481,
    "approval_perbill": 500000000,
    "support_perbill": 1615536,
    "approval": 50,
    "support": 0.1615536
  },
  {
    "time_hours": 482,
    "approval_perbill": 500000000,
    "support_perbill": 1603781,
    "approval": 50,
    "support": 0.1603781
  },
  {
    "time_hours": 483,
    "approval_perbill": 500000000,
    "support_perbill": 1592075,
    "approval": 50,
    "support": 0.1592075
  },
  {
    "time_hours": 484,
    "approval_perbill": 500000000,
    "support_perbill": 1580416,
    "approval": 50,
    "support": 0.1580416
  },
  {
    "time_hours": 485,
    "approval_perbill": 500000000,
    "support_perbill": 1568805,
    "approval": 50,
    "support": 0.1568805
  },
  {
    "time_hours": 486,
    "approval_perbill": 500000000,
    "support_perbill": 1557241,
    "approval": 50,
    "support": 0.1557241
  },
  {
    "time_hours": 487,
    "approval_perbill": 500000000,
    "support_perbill": 1545724,
    "approval": 50,
    "support": 0.1545724
  },
  {
    "time_hours": 488,
    "approval_perbill": 500000000,
    "support_perbill": 1534253,
    "approval": 50,
    "support": 0.1534253
  },
  {
    "time_hours": 489,
    "approval_perbill": 500000000,
    "support_perbill": 1522829,
    "approval": 50,
    "support": 0.1522829
  },
  {
    "time_hours": 490,
    "approval_perbill": 500000000,
    "support_perbill": 1511452,
    "approval": 50,
    "support": 0.1511452
  },
  {
    "time_hours": 491,
    "approval_perbill": 500000000,
    "support_perbill": 1500120,
    "approval": 50,
    "support": 0.150012
  },
  {
    "time_hours": 492,
    "approval_perbill": 500000000,
    "support_perbill": 1488833,
    "approval": 50,
    "support": 0.1488833
  },
  {
    "time_hours": 493,
    "approval_perbill": 500000000,
    "support_perbill": 1477592,
    "approval": 50,
    "support": 0.1477592
  },
  {
    "time_hours": 494,
    "approval_perbill": 500000000,
    "support_perbill": 1466396,
    "approval": 50,
    "support": 0.1466396
  },
  {
    "time_hours": 495,
    "approval_perbill": 500000000,
    "support_perbill": 1455245,
    "approval": 50,
    "support": 0.1455245
  },
  {
    "time_hours": 496,
    "approval_perbill": 500000000,
    "support_perbill": 1444138,
    "approval": 50,
    "support": 0.1444138
  },
  {
    "time_hours": 497,
    "approval_perbill": 500000000,
    "support_perbill": 1433075,
    "approval": 50,
    "support": 0.1433075
  },
  {
    "time_hours": 498,
    "approval_perbill": 500000000,
    "support_perbill": 1422056,
    "approval": 50,
    "support": 0.1422056
  },
  {
    "time_hours": 499,
    "approval_perbill": 500000000,
    "support_perbill": 1411081,
    "approval": 50,
    "support": 0.1411081
  },
  {
    "time_hours": 500,
    "approval_perbill": 500000000,
    "support_perbill": 1400149,
    "approval": 50,
    "support": 0.1400149
  },
  {
    "time_hours": 501,
    "approval_perbill": 500000000,
    "support_perbill": 1389261,
    "approval": 50,
    "support": 0.1389261
  },
  {
    "time_hours": 502,
    "approval_perbill": 500000000,
    "support_perbill": 1378415,
    "approval": 50,
    "support": 0.1378415
  },
  {
    "time_hours": 503,
    "approval_perbill": 500000000,
    "support_perbill": 1367612,
    "approval": 50,
    "support": 0.1367612
  },
  {
    "time_hours": 504,
    "approval_perbill": 500000000,
    "support_perbill": 1356852,
    "approval": 50,
    "support": 0.1356852
  },
  {
    "time_hours": 505,
    "approval_perbill": 500000000,
    "support_perbill": 1346133,
    "approval": 50,
    "support": 0.1346133
  },
  {
    "time_hours": 506,
    "approval_perbill": 500000000,
    "support_perbill": 1335457,
    "approval": 50,
    "support": 0.1335457
  },
  {
    "time_hours": 507,
    "approval_perbill": 500000000,
    "support_perbill": 1324822,
    "approval": 50,
    "support": 0.1324822
  },
  {
    "time_hours": 508,
    "approval_perbill": 500000000,
    "support_perbill": 1314228,
    "approval": 50,
    "support": 0.1314228
  },
  {
    "time_hours": 509,
    "approval_perbill": 500000000,
    "support_perbill": 1303676,
    "approval": 50,
    "support": 0.1303676
  },
  {
    "time_hours": 510,
    "approval_perbill": 500000000,
    "support_perbill": 1293165,
    "approval": 50,
    "support": 0.1293165
  },
  {
    "time_hours": 511,
    "approval_perbill": 500000000,
    "support_perbill": 1282694,
    "approval": 50,
    "support": 0.1282694
  },
  {
    "time_hours": 512,
    "approval_perbill": 500000000,
    "support_perbill": 1272264,
    "approval": 50,
    "support": 0.1272264
  },
  {
    "time_hours": 513,
    "approval_perbill": 500000000,
    "support_perbill": 1261874,
    "approval": 50,
    "support": 0.1261874
  },
  {
    "time_hours": 514,
    "approval_perbill": 500000000,
    "support_perbill": 1251524,
    "approval": 50,
    "support": 0.1251524
  },
  {
    "time_hours": 515,
    "approval_perbill": 500000000,
    "support_perbill": 1241214,
    "approval": 50,
    "support": 0.1241214
  },
  {
    "time_hours": 516,
    "approval_perbill": 500000000,
    "support_perbill": 1230944,
    "approval": 50,
    "support": 0.1230944
  },
  {
    "time_hours": 517,
    "approval_perbill": 500000000,
    "support_perbill": 1220712,
    "approval": 50,
    "support": 0.1220712
  },
  {
    "time_hours": 518,
    "approval_perbill": 500000000,
    "support_perbill": 1210520,
    "approval": 50,
    "support": 0.121052
  },
  {
    "time_hours": 519,
    "approval_perbill": 500000000,
    "support_perbill": 1200367,
    "approval": 50,
    "support": 0.1200367
  },
  {
    "time_hours": 520,
    "approval_perbill": 500000000,
    "support_perbill": 1190252,
    "approval": 50,
    "support": 0.1190252
  },
  {
    "time_hours": 521,
    "approval_perbill": 500000000,
    "support_perbill": 1180176,
    "approval": 50,
    "support": 0.1180176
  },
  {
    "time_hours": 522,
    "approval_perbill": 500000000,
    "support_perbill": 1170138,
    "approval": 50,
    "support": 0.1170138
  },
  {
    "time_hours": 523,
    "approval_perbill": 500000000,
    "support_perbill": 1160137,
    "approval": 50,
    "support": 0.1160137
  },
  {
    "time_hours": 524,
    "approval_perbill": 500000000,
    "support_perbill": 1150175,
    "approval": 50,
    "support": 0.1150175
  },
  {
    "time_hours": 525,
    "approval_perbill": 500000000,
    "support_perbill": 1140250,
    "approval": 50,
    "support": 0.114025
  },
  {
    "time_hours": 526,
    "approval_perbill": 500000000,
    "support_perbill": 1130363,
    "approval": 50,
    "support": 0.1130363
  },
  {
    "time_hours": 527,
    "approval_perbill": 500000000,
    "support_perbill": 1120513,
    "approval": 50,
    "support": 0.1120513
  },
  {
    "time_hours": 528,
    "approval_perbill": 500000000,
    "support_perbill": 1110699,
    "approval": 50,
    "support": 0.1110699
  },
  {
    "time_hours": 529,
    "approval_perbill": 500000000,
    "support_perbill": 1100923,
    "approval": 50,
    "support": 0.1100923
  },
  {
    "time_hours": 530,
    "approval_perbill": 500000000,
    "support_perbill": 1091182,
    "approval": 50,
    "support": 0.1091182
  },
  {
    "time_hours": 531,
    "approval_perbill": 500000000,
    "support_perbill": 1081479,
    "approval": 50,
    "support": 0.1081479
  },
  {
    "time_hours": 532,
    "approval_perbill": 500000000,
    "support_perbill": 1071811,
    "approval": 50,
    "support": 0.1071811
  },
  {
    "time_hours": 533,
    "approval_perbill": 500000000,
    "support_perbill": 1062179,
    "approval": 50,
    "support": 0.1062179
  },
  {
    "time_hours": 534,
    "approval_perbill": 500000000,
    "support_perbill": 1052583,
    "approval": 50,
    "support": 0.1052583
  },
  {
    "time_hours": 535,
    "approval_perbill": 500000000,
    "support_perbill": 1043022,
    "approval": 50,
    "support": 0.1043022
  },
  {
    "time_hours": 536,
    "approval_perbill": 500000000,
    "support_perbill": 1033497,
    "approval": 50,
    "support": 0.1033497
  },
  {
    "time_hours": 537,
    "approval_perbill": 500000000,
    "support_perbill": 1024007,
    "approval": 50,
    "support": 0.1024007
  },
  {
    "time_hours": 538,
    "approval_perbill": 500000000,
    "support_perbill": 1014551,
    "approval": 50,
    "support": 0.1014551
  },
  {
    "time_hours": 539,
    "approval_perbill": 500000000,
    "support_perbill": 1005131,
    "approval": 50,
    "support": 0.1005131
  },
  {
    "time_hours": 540,
    "approval_perbill": 500000000,
    "support_perbill": 995745,
    "approval": 50,
    "support": 0.0995745
  },
  {
    "time_hours": 541,
    "approval_perbill": 500000000,
    "support_perbill": 986393,
    "approval": 50,
    "support": 0.0986393
  },
  {
    "time_hours": 542,
    "approval_perbill": 500000000,
    "support_perbill": 977076,
    "approval": 50,
    "support": 0.0977076
  },
  {
    "time_hours": 543,
    "approval_perbill": 500000000,
    "support_perbill": 967792,
    "approval": 50,
    "support": 0.0967792
  },
  {
    "time_hours": 544,
    "approval_perbill": 500000000,
    "support_perbill": 958542,
    "approval": 50,
    "support": 0.0958542
  },
  {
    "time_hours": 545,
    "approval_perbill": 500000000,
    "support_perbill": 949326,
    "approval": 50,
    "support": 0.0949326
  },
  {
    "time_hours": 546,
    "approval_perbill": 500000000,
    "support_perbill": 940144,
    "approval": 50,
    "support": 0.0940144
  },
  {
    "time_hours": 547,
    "approval_perbill": 500000000,
    "support_perbill": 930994,
    "approval": 50,
    "support": 0.0930994
  },
  {
    "time_hours": 548,
    "approval_perbill": 500000000,
    "support_perbill": 921878,
    "approval": 50,
    "support": 0.0921878
  },
  {
    "time_hours": 549,
    "approval_perbill": 500000000,
    "support_perbill": 912794,
    "approval": 50,
    "support": 0.0912794
  },
  {
    "time_hours": 550,
    "approval_perbill": 500000000,
    "support_perbill": 903743,
    "approval": 50,
    "support": 0.0903743
  },
  {
    "time_hours": 551,
    "approval_perbill": 500000000,
    "support_perbill": 894725,
    "approval": 50,
    "support": 0.0894725
  },
  {
    "time_hours": 552,
    "approval_perbill": 500000000,
    "support_perbill": 885739,
    "approval": 50,
    "support": 0.0885739
  },
  {
    "time_hours": 553,
    "approval_perbill": 500000000,
    "support_perbill": 876785,
    "approval": 50,
    "support": 0.0876785
  },
  {
    "time_hours": 554,
    "approval_perbill": 500000000,
    "support_perbill": 867863,
    "approval": 50,
    "support": 0.0867863
  },
  {
    "time_hours": 555,
    "approval_perbill": 500000000,
    "support_perbill": 858973,
    "approval": 50,
    "support": 0.0858973
  },
  {
    "time_hours": 556,
    "approval_perbill": 500000000,
    "support_perbill": 850115,
    "approval": 50,
    "support": 0.0850115
  },
  {
    "time_hours": 557,
    "approval_perbill": 500000000,
    "support_perbill": 841288,
    "approval": 50,
    "support": 0.0841288
  },
  {
    "time_hours": 558,
    "approval_perbill": 500000000,
    "support_perbill": 832493,
    "approval": 50,
    "support": 0.0832493
  },
  {
    "time_hours": 559,
    "approval_perbill": 500000000,
    "support_perbill": 823729,
    "approval": 50,
    "support": 0.0823729
  },
  {
    "time_hours": 560,
    "approval_perbill": 500000000,
    "support_perbill": 814995,
    "approval": 50,
    "support": 0.0814995
  },
  {
    "time_hours": 561,
    "approval_perbill": 500000000,
    "support_perbill": 806293,
    "approval": 50,
    "support": 0.0806293
  },
  {
    "time_hours": 562,
    "approval_perbill": 500000000,
    "support_perbill": 797621,
    "approval": 50,
    "support": 0.0797621
  },
  {
    "time_hours": 563,
    "approval_perbill": 500000000,
    "support_perbill": 788980,
    "approval": 50,
    "support": 0.078898
  },
  {
    "time_hours": 564,
    "approval_perbill": 500000000,
    "support_perbill": 780369,
    "approval": 50,
    "support": 0.0780369
  },
  {
    "time_hours": 565,
    "approval_perbill": 500000000,
    "support_perbill": 771788,
    "approval": 50,
    "support": 0.0771788
  },
  {
    "time_hours": 566,
    "approval_perbill": 500000000,
    "support_perbill": 763237,
    "approval": 50,
    "support": 0.0763237
  },
  {
    "time_hours": 567,
    "approval_perbill": 500000000,
    "support_perbill": 754716,
    "approval": 50,
    "support": 0.0754716
  },
  {
    "time_hours": 568,
    "approval_perbill": 500000000,
    "support_perbill": 746225,
    "approval": 50,
    "support": 0.0746225
  },
  {
    "time_hours": 569,
    "approval_perbill": 500000000,
    "support_perbill": 737764,
    "approval": 50,
    "support": 0.0737764
  },
  {
    "time_hours": 570,
    "approval_perbill": 500000000,
    "support_perbill": 729331,
    "approval": 50,
    "support": 0.0729331
  },
  {
    "time_hours": 571,
    "approval_perbill": 500000000,
    "support_perbill": 720928,
    "approval": 50,
    "support": 0.0720928
  },
  {
    "time_hours": 572,
    "approval_perbill": 500000000,
    "support_perbill": 712555,
    "approval": 50,
    "support": 0.0712555
  },
  {
    "time_hours": 573,
    "approval_perbill": 500000000,
    "support_perbill": 704210,
    "approval": 50,
    "support": 0.070421
  },
  {
    "time_hours": 574,
    "approval_perbill": 500000000,
    "support_perbill": 695894,
    "approval": 50,
    "support": 0.0695894
  },
  {
    "time_hours": 575,
    "approval_perbill": 500000000,
    "support_perbill": 687606,
    "approval": 50,
    "support": 0.0687606
  },
  {
    "time_hours": 576,
    "approval_perbill": 500000000,
    "support_perbill": 679347,
    "approval": 50,
    "support": 0.0679347
  },
  {
    "time_hours": 577,
    "approval_perbill": 500000000,
    "support_perbill": 671117,
    "approval": 50,
    "support": 0.0671117
  },
  {
    "time_hours": 578,
    "approval_perbill": 500000000,
    "support_perbill": 662914,
    "approval": 50,
    "support": 0.0662914
  },
  {
    "time_hours": 579,
    "approval_perbill": 500000000,
    "support_perbill": 654740,
    "approval": 50,
    "support": 0.065474
  },
  {
    "time_hours": 580,
    "approval_perbill": 500000000,
    "support_perbill": 646594,
    "approval": 50,
    "support": 0.0646594
  },
  {
    "time_hours": 581,
    "approval_perbill": 500000000,
    "support_perbill": 638475,
    "approval": 50,
    "support": 0.0638475
  },
  {
    "time_hours": 582,
    "approval_perbill": 500000000,
    "support_perbill": 630384,
    "approval": 50,
    "support": 0.0630384
  },
  {
    "time_hours": 583,
    "approval_perbill": 500000000,
    "support_perbill": 622320,
    "approval": 50,
    "support": 0.062232
  },
  {
    "time_hours": 584,
    "approval_perbill": 500000000,
    "support_perbill": 614284,
    "approval": 50,
    "support": 0.0614284
  },
  {
    "time_hours": 585,
    "approval_perbill": 500000000,
    "support_perbill": 606275,
    "approval": 50,
    "support": 0.0606275
  },
  {
    "time_hours": 586,
    "approval_perbill": 500000000,
    "support_perbill": 598294,
    "approval": 50,
    "support": 0.0598294
  },
  {
    "time_hours": 587,
    "approval_perbill": 500000000,
    "support_perbill": 590339,
    "approval": 50,
    "support": 0.0590339
  },
  {
    "time_hours": 588,
    "approval_perbill": 500000000,
    "support_perbill": 582411,
    "approval": 50,
    "support": 0.0582411
  },
  {
    "time_hours": 589,
    "approval_perbill": 500000000,
    "support_perbill": 574509,
    "approval": 50,
    "support": 0.0574509
  },
  {
    "time_hours": 590,
    "approval_perbill": 500000000,
    "support_perbill": 566634,
    "approval": 50,
    "support": 0.0566634
  },
  {
    "time_hours": 591,
    "approval_perbill": 500000000,
    "support_perbill": 558786,
    "approval": 50,
    "support": 0.0558786
  },
  {
    "time_hours": 592,
    "approval_perbill": 500000000,
    "support_perbill": 550964,
    "approval": 50,
    "support": 0.0550964
  },
  {
    "time_hours": 593,
    "approval_perbill": 500000000,
    "support_perbill": 543167,
    "approval": 50,
    "support": 0.0543167
  },
  {
    "time_hours": 594,
    "approval_perbill": 500000000,
    "support_perbill": 535397,
    "approval": 50,
    "support": 0.0535397
  },
  {
    "time_hours": 595,
    "approval_perbill": 500000000,
    "support_perbill": 527653,
    "approval": 50,
    "support": 0.0527653
  },
  {
    "time_hours": 596,
    "approval_perbill": 500000000,
    "support_perbill": 519935,
    "approval": 50,
    "support": 0.0519935
  },
  {
    "time_hours": 597,
    "approval_perbill": 500000000,
    "support_perbill": 512242,
    "approval": 50,
    "support": 0.0512242
  },
  {
    "time_hours": 598,
    "approval_perbill": 500000000,
    "support_perbill": 504575,
    "approval": 50,
    "support": 0.0504575
  },
  {
    "time_hours": 599,
    "approval_perbill": 500000000,
    "support_perbill": 496933,
    "approval": 50,
    "support": 0.0496933
  },
  {
    "time_hours": 600,
    "approval_perbill": 500000000,
    "support_perbill": 489316,
    "approval": 50,
    "support": 0.0489316
  },
  {
    "time_hours": 601,
    "approval_perbill": 500000000,
    "support_perbill": 481724,
    "approval": 50,
    "support": 0.0481724
  },
  {
    "time_hours": 602,
    "approval_perbill": 500000000,
    "support_perbill": 474158,
    "approval": 50,
    "support": 0.0474158
  },
  {
    "time_hours": 603,
    "approval_perbill": 500000000,
    "support_perbill": 466616,
    "approval": 50,
    "support": 0.0466616
  },
  {
    "time_hours": 604,
    "approval_perbill": 500000000,
    "support_perbill": 459099,
    "approval": 50,
    "support": 0.0459099
  },
  {
    "time_hours": 605,
    "approval_perbill": 500000000,
    "support_perbill": 451607,
    "approval": 50,
    "support": 0.0451607
  },
  {
    "time_hours": 606,
    "approval_perbill": 500000000,
    "support_perbill": 444139,
    "approval": 50,
    "support": 0.0444139
  },
  {
    "time_hours": 607,
    "approval_perbill": 500000000,
    "support_perbill": 436695,
    "approval": 50,
    "support": 0.0436695
  },
  {
    "time_hours": 608,
    "approval_perbill": 500000000,
    "support_perbill": 429276,
    "approval": 50,
    "support": 0.0429276
  },
  {
    "time_hours": 609,
    "approval_perbill": 500000000,
    "support_perbill": 421881,
    "approval": 50,
    "support": 0.0421881
  },
  {
    "time_hours": 610,
    "approval_perbill": 500000000,
    "support_perbill": 414510,
    "approval": 50,
    "support": 0.041451
  },
  {
    "time_hours": 611,
    "approval_perbill": 500000000,
    "support_perbill": 407163,
    "approval": 50,
    "support": 0.0407163
  },
  {
    "time_hours": 612,
    "approval_perbill": 500000000,
    "support_perbill": 399839,
    "approval": 50,
    "support": 0.0399839
  },
  {
    "time_hours": 613,
    "approval_perbill": 500000000,
    "support_perbill": 392540,
    "approval": 50,
    "support": 0.039254
  },
  {
    "time_hours": 614,
    "approval_perbill": 500000000,
    "support_perbill": 385264,
    "approval": 50,
    "support": 0.0385264
  },
  {
    "time_hours": 615,
    "approval_perbill": 500000000,
    "support_perbill": 378011,
    "approval": 50,
    "support": 0.0378011
  },
  {
    "time_hours": 616,
    "approval_perbill": 500000000,
    "support_perbill": 370782,
    "approval": 50,
    "support": 0.0370782
  },
  {
    "time_hours": 617,
    "approval_perbill": 500000000,
    "support_perbill": 363576,
    "approval": 50,
    "support": 0.0363576
  },
  {
    "time_hours": 618,
    "approval_perbill": 500000000,
    "support_perbill": 356393,
    "approval": 50,
    "support": 0.0356393
  },
  {
    "time_hours": 619,
    "approval_perbill": 500000000,
    "support_perbill": 349233,
    "approval": 50,
    "support": 0.0349233
  },
  {
    "time_hours": 620,
    "approval_perbill": 500000000,
    "support_perbill": 342096,
    "approval": 50,
    "support": 0.0342096
  },
  {
    "time_hours": 621,
    "approval_perbill": 500000000,
    "support_perbill": 334981,
    "approval": 50,
    "support": 0.0334981
  },
  {
    "time_hours": 622,
    "approval_perbill": 500000000,
    "support_perbill": 327890,
    "approval": 50,
    "support": 0.032789
  },
  {
    "time_hours": 623,
    "approval_perbill": 500000000,
    "support_perbill": 320821,
    "approval": 50,
    "support": 0.0320821
  },
  {
    "time_hours": 624,
    "approval_perbill": 500000000,
    "support_perbill": 313774,
    "approval": 50,
    "support": 0.0313774
  },
  {
    "time_hours": 625,
    "approval_perbill": 500000000,
    "support_perbill": 306750,
    "approval": 50,
    "support": 0.030675
  },
  {
    "time_hours": 626,
    "approval_perbill": 500000000,
    "support_perbill": 299748,
    "approval": 50,
    "support": 0.0299748
  },
  {
    "time_hours": 627,
    "approval_perbill": 500000000,
    "support_perbill": 292768,
    "approval": 50,
    "support": 0.0292768
  },
  {
    "time_hours": 628,
    "approval_perbill": 500000000,
    "support_perbill": 285810,
    "approval": 50,
    "support": 0.028581
  },
  {
    "time_hours": 629,
    "approval_perbill": 500000000,
    "support_perbill": 278874,
    "approval": 50,
    "support": 0.0278874
  },
  {
    "time_hours": 630,
    "approval_perbill": 500000000,
    "support_perbill": 271960,
    "approval": 50,
    "support": 0.027196
  },
  {
    "time_hours": 631,
    "approval_perbill": 500000000,
    "support_perbill": 265068,
    "approval": 50,
    "support": 0.0265068
  },
  {
    "time_hours": 632,
    "approval_perbill": 500000000,
    "support_perbill": 258197,
    "approval": 50,
    "support": 0.0258197
  },
  {
    "time_hours": 633,
    "approval_perbill": 500000000,
    "support_perbill": 251348,
    "approval": 50,
    "support": 0.0251348
  },
  {
    "time_hours": 634,
    "approval_perbill": 500000000,
    "support_perbill": 244520,
    "approval": 50,
    "support": 0.024452
  },
  {
    "time_hours": 635,
    "approval_perbill": 500000000,
    "support_perbill": 237714,
    "approval": 50,
    "support": 0.0237714
  },
  {
    "time_hours": 636,
    "approval_perbill": 500000000,
    "support_perbill": 230928,
    "approval": 50,
    "support": 0.0230928
  },
  {
    "time_hours": 637,
    "approval_perbill": 500000000,
    "support_perbill": 224164,
    "approval": 50,
    "support": 0.0224164
  },
  {
    "time_hours": 638,
    "approval_perbill": 500000000,
    "support_perbill": 217421,
    "approval": 50,
    "support": 0.0217421
  },
  {
    "time_hours": 639,
    "approval_perbill": 500000000,
    "support_perbill": 210699,
    "approval": 50,
    "support": 0.0210699
  },
  {
    "time_hours": 640,
    "approval_perbill": 500000000,
    "support_perbill": 203998,
    "approval": 50,
    "support": 0.0203998
  },
  {
    "time_hours": 641,
    "approval_perbill": 500000000,
    "support_perbill": 197317,
    "approval": 50,
    "support": 0.0197317
  },
  {
    "time_hours": 642,
    "approval_perbill": 500000000,
    "support_perbill": 190657,
    "approval": 50,
    "support": 0.0190657
  },
  {
    "time_hours": 643,
    "approval_perbill": 500000000,
    "support_perbill": 184018,
    "approval": 50,
    "support": 0.0184018
  },
  {
    "time_hours": 644,
    "approval_perbill": 500000000,
    "support_perbill": 177399,
    "approval": 50,
    "support": 0.0177399
  },
  {
    "time_hours": 645,
    "approval_perbill": 500000000,
    "support_perbill": 170800,
    "approval": 50,
    "support": 0.01708
  },
  {
    "time_hours": 646,
    "approval_perbill": 500000000,
    "support_perbill": 164222,
    "approval": 50,
    "support": 0.0164222
  },
  {
    "time_hours": 647,
    "approval_perbill": 500000000,
    "support_perbill": 157663,
    "approval": 50,
    "support": 0.0157663
  },
  {
    "time_hours": 648,
    "approval_perbill": 500000000,
    "support_perbill": 151125,
    "approval": 50,
    "support": 0.0151125
  },
  {
    "time_hours": 649,
    "approval_perbill": 500000000,
    "support_perbill": 144607,
    "approval": 50,
    "support": 0.0144607
  },
  {
    "time_hours": 650,
    "approval_perbill": 500000000,
    "support_perbill": 138109,
    "approval": 50,
    "support": 0.0138109
  },
  {
    "time_hours": 651,
    "approval_perbill": 500000000,
    "support_perbill": 131630,
    "approval": 50,
    "support": 0.013163
  },
  {
    "time_hours": 652,
    "approval_perbill": 500000000,
    "support_perbill": 125171,
    "approval": 50,
    "support": 0.0125171
  },
  {
    "time_hours": 653,
    "approval_perbill": 500000000,
    "support_perbill": 118732,
    "approval": 50,
    "support": 0.0118732
  },
  {
    "time_hours": 654,
    "approval_perbill": 500000000,
    "support_perbill": 112313,
    "approval": 50,
    "support": 0.0112313
  },
  {
    "time_hours": 655,
    "approval_perbill": 500000000,
    "support_perbill": 105912,
    "approval": 50,
    "support": 0.0105912
  },
  {
    "time_hours": 656,
    "approval_perbill": 500000000,
    "support_perbill": 99532,
    "approval": 50,
    "support": 0.0099532
  },
  {
    "time_hours": 657,
    "approval_perbill": 500000000,
    "support_perbill": 93170,
    "approval": 50,
    "support": 0.009317
  },
  {
    "time_hours": 658,
    "approval_perbill": 500000000,
    "support_perbill": 86827,
    "approval": 50,
    "support": 0.0086827
  },
  {
    "time_hours": 659,
    "approval_perbill": 500000000,
    "support_perbill": 80504,
    "approval": 50,
    "support": 0.0080504
  },
  {
    "time_hours": 660,
    "approval_perbill": 500000000,
    "support_perbill": 74200,
    "approval": 50,
    "support": 0.00742
  },
  {
    "time_hours": 661,
    "approval_perbill": 500000000,
    "support_perbill": 67914,
    "approval": 50,
    "support": 0.0067914
  },
  {
    "time_hours": 662,
    "approval_perbill": 500000000,
    "support_perbill": 61648,
    "approval": 50,
    "support": 0.0061648
  },
  {
    "time_hours": 663,
    "approval_perbill": 500000000,
    "support_perbill": 55400,
    "approval": 50,
    "support": 0.00554
  },
  {
    "time_hours": 664,
    "approval_perbill": 500000000,
    "support_perbill": 49171,
    "approval": 50,
    "support": 0.0049171
  },
  {
    "time_hours": 665,
    "approval_perbill": 500000000,
    "support_perbill": 42960,
    "approval": 50,
    "support": 0.004296
  },
  {
    "time_hours": 666,
    "approval_perbill": 500000000,
    "support_perbill": 36768,
    "approval": 50,
    "support": 0.0036768
  },
  {
    "time_hours": 667,
    "approval_perbill": 500000000,
    "support_perbill": 30594,
    "approval": 50,
    "support": 0.0030594
  },
  {
    "time_hours": 668,
    "approval_perbill": 500000000,
    "support_perbill": 24439,
    "approval": 50,
    "support": 0.0024439
  },
  {
    "time_hours": 669,
    "approval_perbill": 500000000,
    "support_perbill": 18302,
    "approval": 50,
    "support": 0.0018302
  },
  {
    "time_hours": 670,
    "approval_perbill": 500000000,
    "support_perbill": 12183,
    "approval": 50,
    "support": 0.0012183
  },
  {
    "time_hours": 671,
    "approval_perbill": 500000000,
    "support_perbill": 6082,
    "approval": 50,
    "support": 0.0006082
  },
  {
    "time_hours": 672,
    "approval_perbill": 500000000,
    "support_perbill": 0,
    "approval": 50,
    "support": 0
  }
]